RGB_Mixer/pwm_driver.sv
module pwm_driver(
input wire clk,
input wire rst,
input wire [7:0] duty_cycle,
output reg pwm_out
);
reg [7:0] cycle;
reg [7:0] counter;


// Calculate cycle value
always @(duty_cycle) begin
    cycle = duty_cycle / 5.1; // Approximation of duty_cycle / 2.55
end

always @(posedge clk or posedge rst) begin 
    if (rst) begin 
        pwm_out <= 1'b0;
        counter <= 8'b0;
    end 
    else begin
        if (counter < 8'd50) 
            counter <= counter + 8'd1; 
        else 
            counter <= 8'd0; 

        pwm_out <= (counter < cycle) ? 1'b1 : 1'b0;
    end 
end 
endmodule

RGB_Mixer/rotary_encoder.sv
module rotary_encoder(

    input clk, rst,
    input A, B,
    output reg [7:0] count

);
    reg Aprev, Bprev;

    always_ff @( posedge clk or posedge rst ) begin : encoder
    
    if (rst) begin 
        Aprev <= 1'b0;
        Bprev <= 1'b0;
        count <= 0;
    end else begin 
        Aprev <= A;
        Bprev <= B;
        if (A && !Aprev) begin 
            count <= count + 1;
        end 
        if (B && !Bprev) begin 

            count  <= count - 1;
        end
    end 
    end    
endmodule

RGB_Mixer/led-driver.sv
module rgb_led_driver(
    input clk, rst,
    input encoder_A, encoder_B,
    output pwm_red, pwm_green, pwm_blue
);

    
    wire [7:0] red_counter;
    wire [7:0] green_counter;
    wire [7:0] blue_counter;
    
    rotary_encoder encoder_red (
        .clk(clk),
        .rst(rst),
        .A(encoder_A),
        .B(encoder_B),
        .count(red_counter)
    );

    pwm_driver driver_red (
        .clk(clk),
        .rst(rst),
        .duty_cycle(red_counter),
        .pwm_out(pwm_red)
    );

    rotary_encoder encoder_green (
        .clk(clk),
        .rst(rst),
        .A(encoder_A),
        .B(encoder_B),
        .count(green_counter)
    );

    pwm_driver driver_green (
        .clk(clk),
        .rst(rst),
        .duty_cycle(red_counter),
        .pwm_out(pwm_green)
    );

    rotary_encoder encoder_blue (
        .clk(clk),
        .rst(rst),
        .A(encoder_A),
        .B(encoder_B),
        .count(blue_counter)
    );

    pwm_driver driver_blue (
        .clk(clk),
        .rst(rst),
        .duty_cycle(red_counter),
        .pwm_out(pwm_blue)
    );
    
    always @(posedge clk) begin
        $display("Red: %d, Green: %d, Blue: %d", red_counter, green_counter, blue_counter);
    end
endmodule

RGB_Mixer/led_driver_tb.sv
`timescale 1ns / 1ps

module led_driver_tb;

    reg clk;
    reg rst;
    reg A;
    reg B;

    wire pwm_red;
    wire pwm_green;
    wire pwm_blue;

    rgb_led_driver uut(
        .clk(clk),
        .rst(rst),
        .encoder_A(A),
        .encoder_B(B),
        .pwm_red(pwm_red),
        .pwm_blue(pwm_blue),
        .pwm_green(pwm_green)
    );

  // Clock generation
  always begin
    clk = 1'b0;
    #5;
    clk = 1'b1;
    #5;
  end

initial begin
    // Initialize inputs
    rst = 1'b1;
    A = 1'b0;
    B = 1'b0;

    // Reset
    #20 rst = 1'b0;

    // Test clockwise rotation
    #20 A = 1'b1;
    #10 B = 1'b1;
    #10 A = 1'b0;
    #10 B = 1'b0;

    // Test counter-clockwise rotation
    #20 B = 1'b1;
    #10 A = 1'b1;
    #10 B = 1'b0;
    #10 A = 1'b0;

    // Test multiple rotations
    repeat(10) begin
    #10 A = 1'b1;
    #10 B = 1'b1;
    #10 A = 1'b0;
    #10 B = 1'b0;
    
    end
    #1000

    repeat(60) begin
    #10 A = 1'b1;
    #10 B = 1'b1;
    #10 A = 1'b0;
    #10 B = 1'b0;
    
    end
    #1000

    // End simulation
    #100 $finish;
  end


 // VCD file generation
  initial begin
      $dumpfile("led_driver.vcd");
      $dumpvars(0, led_driver_tb);
  end

initial begin
    $monitor("Time=%0t rst=%b A=%b B=%b", $time, rst, A, B );
  end
endmodule

RGB_Mixer/led_driver.vcd
$date
	Wed Oct 09 16:16:47 2024
$end
$version
	Icarus Verilog
$end
$timescale
	1ps
$end
$scope module led_driver_tb $end
$var wire 1 ! pwm_red $end
$var wire 1 " pwm_green $end
$var wire 1 # pwm_blue $end
$var reg 1 $ A $end
$var reg 1 % B $end
$var reg 1 & clk $end
$var reg 1 ' rst $end
$scope module uut $end
$var wire 1 & clk $end
$var wire 1 $ encoder_A $end
$var wire 1 % encoder_B $end
$var wire 1 ' rst $end
$var wire 8 ( red_counter [7:0] $end
$var wire 1 ! pwm_red $end
$var wire 1 " pwm_green $end
$var wire 1 # pwm_blue $end
$var wire 8 ) green_counter [7:0] $end
$var wire 8 * blue_counter [7:0] $end
$scope module driver_blue $end
$var wire 1 & clk $end
$var wire 1 ' rst $end
$var wire 8 + duty_cycle [7:0] $end
$var reg 8 , counter [7:0] $end
$var reg 8 - cycle [7:0] $end
$var reg 1 # pwm_out $end
$upscope $end
$scope module driver_green $end
$var wire 1 & clk $end
$var wire 1 ' rst $end
$var wire 8 . duty_cycle [7:0] $end
$var reg 8 / counter [7:0] $end
$var reg 8 0 cycle [7:0] $end
$var reg 1 " pwm_out $end
$upscope $end
$scope module driver_red $end
$var wire 1 & clk $end
$var wire 1 ' rst $end
$var wire 8 1 duty_cycle [7:0] $end
$var reg 8 2 counter [7:0] $end
$var reg 8 3 cycle [7:0] $end
$var reg 1 ! pwm_out $end
$upscope $end
$scope module encoder_blue $end
$var wire 1 $ A $end
$var wire 1 % B $end
$var wire 1 & clk $end
$var wire 1 ' rst $end
$var reg 1 4 Aprev $end
$var reg 1 5 Bprev $end
$var reg 8 6 count [7:0] $end
$scope begin encoder $end
$upscope $end
$upscope $end
$scope module encoder_green $end
$var wire 1 $ A $end
$var wire 1 % B $end
$var wire 1 & clk $end
$var wire 1 ' rst $end
$var reg 1 7 Aprev $end
$var reg 1 8 Bprev $end
$var reg 8 9 count [7:0] $end
$scope begin encoder $end
$upscope $end
$upscope $end
$scope module encoder_red $end
$var wire 1 $ A $end
$var wire 1 % B $end
$var wire 1 & clk $end
$var wire 1 ' rst $end
$var reg 1 : Aprev $end
$var reg 1 ; Bprev $end
$var reg 8 < count [7:0] $end
$scope begin encoder $end
$upscope $end
$upscope $end
$upscope $end
$upscope $end
$enddefinitions $end
$comment Show the parameter values. $end
$dumpall
$end
#0
$dumpvars
b0 <
0;
0:
b0 9
08
07
b0 6
05
04
b0 3
b0 2
b0 1
b0 0
b0 /
b0 .
b0 -
b0 ,
b0 +
b0 *
b0 )
b0 (
1'
0&
0%
0$
0#
0"
0!
$end
#5000
1&
#10000
0&
#15000
1&
#20000
0&
0'
#25000
b1 ,
b1 /
b1 2
1&
#30000
0&
#35000
b10 2
b10 /
b10 ,
1&
#40000
0&
1$
#45000
b1 *
b1 6
14
b1 )
b1 9
17
b1 (
b1 +
b1 .
b1 1
b1 <
1:
b11 ,
b11 /
b11 2
1&
#50000
0&
1%
#55000
b10 *
b10 6
15
b10 )
b10 9
18
b10 (
b10 +
b10 .
b10 1
b10 <
1;
b100 2
b100 /
b100 ,
1&
#60000
0&
0$
#65000
04
07
0:
b101 ,
b101 /
b101 2
1&
#70000
0&
0%
#75000
05
08
0;
b110 2
b110 /
b110 ,
1&
#80000
0&
#85000
b111 ,
b111 /
b111 2
1&
#90000
0&
1%
#95000
b1 *
b1 6
15
b1 )
b1 9
18
b1 (
b1 +
b1 .
b1 1
b1 <
1;
b1000 2
b1000 /
b1000 ,
1&
#100000
0&
1$
#105000
b0 *
b0 6
14
b0 )
b0 9
17
b0 (
b0 +
b0 .
b0 1
b0 <
1:
b1001 ,
b1001 /
b1001 2
1&
#110000
0&
0%
#115000
05
08
0;
b1010 2
b1010 /
b1010 ,
1&
#120000
0&
0$
#125000
04
07
0:
b1011 ,
b1011 /
b1011 2
1&
#130000
0&
1$
#135000
b1 *
b1 6
14
b1 )
b1 9
17
b1 (
b1 +
b1 .
b1 1
b1 <
1:
b1100 2
b1100 /
b1100 ,
1&
#140000
0&
1%
#145000
b10 *
b10 6
15
b10 )
b10 9
18
b10 (
b10 +
b10 .
b10 1
b10 <
1;
b1101 ,
b1101 /
b1101 2
1&
#150000
0&
0$
#155000
04
07
0:
b1110 2
b1110 /
b1110 ,
1&
#160000
0&
0%
#165000
05
08
0;
b1111 ,
b1111 /
b1111 2
1&
#170000
0&
1$
#175000
b1 3
b1 0
b1 -
b11 *
b11 6
14
b11 )
b11 9
17
b11 (
b11 +
b11 .
b11 1
b11 <
1:
b10000 2
b10000 /
b10000 ,
1&
#180000
0&
1%
#185000
b100 *
b100 6
15
b100 )
b100 9
18
b100 (
b100 +
b100 .
b100 1
b100 <
1;
b10001 ,
b10001 /
b10001 2
1&
#190000
0&
0$
#195000
04
07
0:
b10010 2
b10010 /
b10010 ,
1&
#200000
0&
0%
#205000
05
08
0;
b10011 ,
b10011 /
b10011 2
1&
#210000
0&
1$
#215000
b101 *
b101 6
14
b101 )
b101 9
17
b101 (
b101 +
b101 .
b101 1
b101 <
1:
b10100 2
b10100 /
b10100 ,
1&
#220000
0&
1%
#225000
b110 *
b110 6
15
b110 )
b110 9
18
b110 (
b110 +
b110 .
b110 1
b110 <
1;
b10101 ,
b10101 /
b10101 2
1&
#230000
0&
0$
#235000
04
07
0:
b10110 2
b10110 /
b10110 ,
1&
#240000
0&
0%
#245000
05
08
0;
b10111 ,
b10111 /
b10111 2
1&
#250000
0&
1$
#255000
b111 *
b111 6
14
b111 )
b111 9
17
b111 (
b111 +
b111 .
b111 1
b111 <
1:
b11000 2
b11000 /
b11000 ,
1&
#260000
0&
1%
#265000
b10 -
b10 0
b10 3
b1000 *
b1000 6
15
b1000 )
b1000 9
18
b1000 (
b1000 +
b1000 .
b1000 1
b1000 <
1;
b11001 ,
b11001 /
b11001 2
1&
#270000
0&
0$
#275000
04
07
0:
b11010 2
b11010 /
b11010 ,
1&
#280000
0&
0%
#285000
05
08
0;
b11011 ,
b11011 /
b11011 2
1&
#290000
0&
1$
#295000
b1001 *
b1001 6
14
b1001 )
b1001 9
17
b1001 (
b1001 +
b1001 .
b1001 1
b1001 <
1:
b11100 2
b11100 /
b11100 ,
1&
#300000
0&
1%
#305000
b1010 *
b1010 6
15
b1010 )
b1010 9
18
b1010 (
b1010 +
b1010 .
b1010 1
b1010 <
1;
b11101 ,
b11101 /
b11101 2
1&
#310000
0&
0$
#315000
04
07
0:
b11110 2
b11110 /
b11110 ,
1&
#320000
0&
0%
#325000
05
08
0;
b11111 ,
b11111 /
b11111 2
1&
#330000
0&
1$
#335000
b1011 *
b1011 6
14
b1011 )
b1011 9
17
b1011 (
b1011 +
b1011 .
b1011 1
b1011 <
1:
b100000 2
b100000 /
b100000 ,
1&
#340000
0&
1%
#345000
b1100 *
b1100 6
15
b1100 )
b1100 9
18
b1100 (
b1100 +
b1100 .
b1100 1
b1100 <
1;
b100001 ,
b100001 /
b100001 2
1&
#350000
0&
0$
#355000
04
07
0:
b100010 2
b100010 /
b100010 ,
1&
#360000
0&
0%
#365000
05
08
0;
b100011 ,
b100011 /
b100011 2
1&
#370000
0&
1$
#375000
b11 3
b11 0
b11 -
b1101 *
b1101 6
14
b1101 )
b1101 9
17
b1101 (
b1101 +
b1101 .
b1101 1
b1101 <
1:
b100100 2
b100100 /
b100100 ,
1&
#380000
0&
1%
#385000
b1110 *
b1110 6
15
b1110 )
b1110 9
18
b1110 (
b1110 +
b1110 .
b1110 1
b1110 <
1;
b100101 ,
b100101 /
b100101 2
1&
#390000
0&
0$
#395000
04
07
0:
b100110 2
b100110 /
b100110 ,
1&
#400000
0&
0%
#405000
05
08
0;
b100111 ,
b100111 /
b100111 2
1&
#410000
0&
1$
#415000
b1111 *
b1111 6
14
b1111 )
b1111 9
17
b1111 (
b1111 +
b1111 .
b1111 1
b1111 <
1:
b101000 2
b101000 /
b101000 ,
1&
#420000
0&
1%
#425000
b10000 *
b10000 6
15
b10000 )
b10000 9
18
b10000 (
b10000 +
b10000 .
b10000 1
b10000 <
1;
b101001 ,
b101001 /
b101001 2
1&
#430000
0&
0$
#435000
04
07
0:
b101010 2
b101010 /
b101010 ,
1&
#440000
0&
0%
#445000
05
08
0;
b101011 ,
b101011 /
b101011 2
1&
#450000
0&
1$
#455000
b10001 *
b10001 6
14
b10001 )
b10001 9
17
b10001 (
b10001 +
b10001 .
b10001 1
b10001 <
1:
b101100 2
b101100 /
b101100 ,
1&
#460000
0&
1%
#465000
b100 -
b100 0
b100 3
b10010 *
b10010 6
15
b10010 )
b10010 9
18
b10010 (
b10010 +
b10010 .
b10010 1
b10010 <
1;
b101101 ,
b101101 /
b101101 2
1&
#470000
0&
0$
#475000
04
07
0:
b101110 2
b101110 /
b101110 ,
1&
#480000
0&
0%
#485000
05
08
0;
b101111 ,
b101111 /
b101111 2
1&
#490000
0&
1$
#495000
b10011 *
b10011 6
14
b10011 )
b10011 9
17
b10011 (
b10011 +
b10011 .
b10011 1
b10011 <
1:
b110000 2
b110000 /
b110000 ,
1&
#500000
0&
1%
#505000
b10100 *
b10100 6
15
b10100 )
b10100 9
18
b10100 (
b10100 +
b10100 .
b10100 1
b10100 <
1;
b110001 ,
b110001 /
b110001 2
1&
#510000
0&
0$
#515000
04
07
0:
b110010 2
b110010 /
b110010 ,
1&
#520000
0&
0%
#525000
05
08
0;
b0 ,
b0 /
b0 2
1&
#530000
0&
#535000
1!
b1 2
1"
b1 /
1#
b1 ,
1&
#540000
0&
#545000
b10 ,
b10 /
b10 2
1&
#550000
0&
#555000
b11 2
b11 /
b11 ,
1&
#560000
0&
#565000
b100 ,
b100 /
b100 2
1&
#570000
0&
#575000
0!
b101 2
0"
b101 /
0#
b101 ,
1&
#580000
0&
#585000
b110 ,
b110 /
b110 2
1&
#590000
0&
#595000
b111 2
b111 /
b111 ,
1&
#600000
0&
#605000
b1000 ,
b1000 /
b1000 2
1&
#610000
0&
#615000
b1001 2
b1001 /
b1001 ,
1&
#620000
0&
#625000
b1010 ,
b1010 /
b1010 2
1&
#630000
0&
#635000
b1011 2
b1011 /
b1011 ,
1&
#640000
0&
#645000
b1100 ,
b1100 /
b1100 2
1&
#650000
0&
#655000
b1101 2
b1101 /
b1101 ,
1&
#660000
0&
#665000
b1110 ,
b1110 /
b1110 2
1&
#670000
0&
#675000
b1111 2
b1111 /
b1111 ,
1&
#680000
0&
#685000
b10000 ,
b10000 /
b10000 2
1&
#690000
0&
#695000
b10001 2
b10001 /
b10001 ,
1&
#700000
0&
#705000
b10010 ,
b10010 /
b10010 2
1&
#710000
0&
#715000
b10011 2
b10011 /
b10011 ,
1&
#720000
0&
#725000
b10100 ,
b10100 /
b10100 2
1&
#730000
0&
#735000
b10101 2
b10101 /
b10101 ,
1&
#740000
0&
#745000
b10110 ,
b10110 /
b10110 2
1&
#750000
0&
#755000
b10111 2
b10111 /
b10111 ,
1&
#760000
0&
#765000
b11000 ,
b11000 /
b11000 2
1&
#770000
0&
#775000
b11001 2
b11001 /
b11001 ,
1&
#780000
0&
#785000
b11010 ,
b11010 /
b11010 2
1&
#790000
0&
#795000
b11011 2
b11011 /
b11011 ,
1&
#800000
0&
#805000
b11100 ,
b11100 /
b11100 2
1&
#810000
0&
#815000
b11101 2
b11101 /
b11101 ,
1&
#820000
0&
#825000
b11110 ,
b11110 /
b11110 2
1&
#830000
0&
#835000
b11111 2
b11111 /
b11111 ,
1&
#840000
0&
#845000
b100000 ,
b100000 /
b100000 2
1&
#850000
0&
#855000
b100001 2
b100001 /
b100001 ,
1&
#860000
0&
#865000
b100010 ,
b100010 /
b100010 2
1&
#870000
0&
#875000
b100011 2
b100011 /
b100011 ,
1&
#880000
0&
#885000
b100100 ,
b100100 /
b100100 2
1&
#890000
0&
#895000
b100101 2
b100101 /
b100101 ,
1&
#900000
0&
#905000
b100110 ,
b100110 /
b100110 2
1&
#910000
0&
#915000
b100111 2
b100111 /
b100111 ,
1&
#920000
0&
#925000
b101000 ,
b101000 /
b101000 2
1&
#930000
0&
#935000
b101001 2
b101001 /
b101001 ,
1&
#940000
0&
#945000
b101010 ,
b101010 /
b101010 2
1&
#950000
0&
#955000
b101011 2
b101011 /
b101011 ,
1&
#960000
0&
#965000
b101100 ,
b101100 /
b101100 2
1&
#970000
0&
#975000
b101101 2
b101101 /
b101101 ,
1&
#980000
0&
#985000
b101110 ,
b101110 /
b101110 2
1&
#990000
0&
#995000
b101111 2
b101111 /
b101111 ,
1&
#1000000
0&
#1005000
b110000 ,
b110000 /
b110000 2
1&
#1010000
0&
#1015000
b110001 2
b110001 /
b110001 ,
1&
#1020000
0&
#1025000
b110010 ,
b110010 /
b110010 2
1&
#1030000
0&
#1035000
b0 2
b0 /
b0 ,
1&
#1040000
0&
#1045000
1#
b1 ,
1"
b1 /
1!
b1 2
1&
#1050000
0&
#1055000
b10 2
b10 /
b10 ,
1&
#1060000
0&
#1065000
b11 ,
b11 /
b11 2
1&
#1070000
0&
#1075000
b100 2
b100 /
b100 ,
1&
#1080000
0&
#1085000
0#
b101 ,
0"
b101 /
0!
b101 2
1&
#1090000
0&
#1095000
b110 2
b110 /
b110 ,
1&
#1100000
0&
#1105000
b111 ,
b111 /
b111 2
1&
#1110000
0&
#1115000
b1000 2
b1000 /
b1000 ,
1&
#1120000
0&
#1125000
b1001 ,
b1001 /
b1001 2
1&
#1130000
0&
#1135000
b1010 2
b1010 /
b1010 ,
1&
#1140000
0&
#1145000
b1011 ,
b1011 /
b1011 2
1&
#1150000
0&
#1155000
b1100 2
b1100 /
b1100 ,
1&
#1160000
0&
#1165000
b1101 ,
b1101 /
b1101 2
1&
#1170000
0&
#1175000
b1110 2
b1110 /
b1110 ,
1&
#1180000
0&
#1185000
b1111 ,
b1111 /
b1111 2
1&
#1190000
0&
#1195000
b10000 2
b10000 /
b10000 ,
1&
#1200000
0&
#1205000
b10001 ,
b10001 /
b10001 2
1&
#1210000
0&
#1215000
b10010 2
b10010 /
b10010 ,
1&
#1220000
0&
#1225000
b10011 ,
b10011 /
b10011 2
1&
#1230000
0&
#1235000
b10100 2
b10100 /
b10100 ,
1&
#1240000
0&
#1245000
b10101 ,
b10101 /
b10101 2
1&
#1250000
0&
#1255000
b10110 2
b10110 /
b10110 ,
1&
#1260000
0&
#1265000
b10111 ,
b10111 /
b10111 2
1&
#1270000
0&
#1275000
b11000 2
b11000 /
b11000 ,
1&
#1280000
0&
#1285000
b11001 ,
b11001 /
b11001 2
1&
#1290000
0&
#1295000
b11010 2
b11010 /
b11010 ,
1&
#1300000
0&
#1305000
b11011 ,
b11011 /
b11011 2
1&
#1310000
0&
#1315000
b11100 2
b11100 /
b11100 ,
1&
#1320000
0&
#1325000
b11101 ,
b11101 /
b11101 2
1&
#1330000
0&
#1335000
b11110 2
b11110 /
b11110 ,
1&
#1340000
0&
#1345000
b11111 ,
b11111 /
b11111 2
1&
#1350000
0&
#1355000
b100000 2
b100000 /
b100000 ,
1&
#1360000
0&
#1365000
b100001 ,
b100001 /
b100001 2
1&
#1370000
0&
#1375000
b100010 2
b100010 /
b100010 ,
1&
#1380000
0&
#1385000
b100011 ,
b100011 /
b100011 2
1&
#1390000
0&
#1395000
b100100 2
b100100 /
b100100 ,
1&
#1400000
0&
#1405000
b100101 ,
b100101 /
b100101 2
1&
#1410000
0&
#1415000
b100110 2
b100110 /
b100110 ,
1&
#1420000
0&
#1425000
b100111 ,
b100111 /
b100111 2
1&
#1430000
0&
#1435000
b101000 2
b101000 /
b101000 ,
1&
#1440000
0&
#1445000
b101001 ,
b101001 /
b101001 2
1&
#1450000
0&
#1455000
b101010 2
b101010 /
b101010 ,
1&
#1460000
0&
#1465000
b101011 ,
b101011 /
b101011 2
1&
#1470000
0&
#1475000
b101100 2
b101100 /
b101100 ,
1&
#1480000
0&
#1485000
b101101 ,
b101101 /
b101101 2
1&
#1490000
0&
#1495000
b101110 2
b101110 /
b101110 ,
1&
#1500000
0&
#1505000
b101111 ,
b101111 /
b101111 2
1&
#1510000
0&
#1515000
b110000 2
b110000 /
b110000 ,
1&
#1520000
0&
#1525000
b110001 ,
b110001 /
b110001 2
1&
#1530000
0&
1$
#1535000
b10101 *
b10101 6
14
b10101 )
b10101 9
17
b10101 (
b10101 +
b10101 .
b10101 1
b10101 <
1:
b110010 2
b110010 /
b110010 ,
1&
#1540000
0&
1%
#1545000
b10110 *
b10110 6
15
b10110 )
b10110 9
18
b10110 (
b10110 +
b10110 .
b10110 1
b10110 <
1;
b0 ,
b0 /
b0 2
1&
#1550000
0&
0$
#1555000
04
07
0:
1!
b1 2
1"
b1 /
1#
b1 ,
1&
#1560000
0&
0%
#1565000
05
08
0;
b10 ,
b10 /
b10 2
1&
#1570000
0&
1$
#1575000
b101 3
b101 0
b101 -
b10111 *
b10111 6
14
b10111 )
b10111 9
17
b10111 (
b10111 +
b10111 .
b10111 1
b10111 <
1:
b11 2
b11 /
b11 ,
1&
#1580000
0&
1%
#1585000
b11000 *
b11000 6
15
b11000 )
b11000 9
18
b11000 (
b11000 +
b11000 .
b11000 1
b11000 <
1;
b100 ,
b100 /
b100 2
1&
#1590000
0&
0$
#1595000
04
07
0:
b101 2
b101 /
b101 ,
1&
#1600000
0&
0%
#1605000
05
08
0;
0#
b110 ,
0"
b110 /
0!
b110 2
1&
#1610000
0&
1$
#1615000
b11001 *
b11001 6
14
b11001 )
b11001 9
17
b11001 (
b11001 +
b11001 .
b11001 1
b11001 <
1:
b111 2
b111 /
b111 ,
1&
#1620000
0&
1%
#1625000
b11010 *
b11010 6
15
b11010 )
b11010 9
18
b11010 (
b11010 +
b11010 .
b11010 1
b11010 <
1;
b1000 ,
b1000 /
b1000 2
1&
#1630000
0&
0$
#1635000
04
07
0:
b1001 2
b1001 /
b1001 ,
1&
#1640000
0&
0%
#1645000
05
08
0;
b1010 ,
b1010 /
b1010 2
1&
#1650000
0&
1$
#1655000
b11011 *
b11011 6
14
b11011 )
b11011 9
17
b11011 (
b11011 +
b11011 .
b11011 1
b11011 <
1:
b1011 2
b1011 /
b1011 ,
1&
#1660000
0&
1%
#1665000
b11100 *
b11100 6
15
b11100 )
b11100 9
18
b11100 (
b11100 +
b11100 .
b11100 1
b11100 <
1;
b1100 ,
b1100 /
b1100 2
1&
#1670000
0&
0$
#1675000
04
07
0:
b1101 2
b1101 /
b1101 ,
1&
#1680000
0&
0%
#1685000
05
08
0;
b1110 ,
b1110 /
b1110 2
1&
#1690000
0&
1$
#1695000
b110 3
b110 0
b110 -
b11101 *
b11101 6
14
b11101 )
b11101 9
17
b11101 (
b11101 +
b11101 .
b11101 1
b11101 <
1:
b1111 2
b1111 /
b1111 ,
1&
#1700000
0&
1%
#1705000
b11110 *
b11110 6
15
b11110 )
b11110 9
18
b11110 (
b11110 +
b11110 .
b11110 1
b11110 <
1;
b10000 ,
b10000 /
b10000 2
1&
#1710000
0&
0$
#1715000
04
07
0:
b10001 2
b10001 /
b10001 ,
1&
#1720000
0&
0%
#1725000
05
08
0;
b10010 ,
b10010 /
b10010 2
1&
#1730000
0&
1$
#1735000
b11111 *
b11111 6
14
b11111 )
b11111 9
17
b11111 (
b11111 +
b11111 .
b11111 1
b11111 <
1:
b10011 2
b10011 /
b10011 ,
1&
#1740000
0&
1%
#1745000
b100000 *
b100000 6
15
b100000 )
b100000 9
18
b100000 (
b100000 +
b100000 .
b100000 1
b100000 <
1;
b10100 ,
b10100 /
b10100 2
1&
#1750000
0&
0$
#1755000
04
07
0:
b10101 2
b10101 /
b10101 ,
1&
#1760000
0&
0%
#1765000
05
08
0;
b10110 ,
b10110 /
b10110 2
1&
#1770000
0&
1$
#1775000
b100001 *
b100001 6
14
b100001 )
b100001 9
17
b100001 (
b100001 +
b100001 .
b100001 1
b100001 <
1:
b10111 2
b10111 /
b10111 ,
1&
#1780000
0&
1%
#1785000
b111 -
b111 0
b111 3
b100010 *
b100010 6
15
b100010 )
b100010 9
18
b100010 (
b100010 +
b100010 .
b100010 1
b100010 <
1;
b11000 ,
b11000 /
b11000 2
1&
#1790000
0&
0$
#1795000
04
07
0:
b11001 2
b11001 /
b11001 ,
1&
#1800000
0&
0%
#1805000
05
08
0;
b11010 ,
b11010 /
b11010 2
1&
#1810000
0&
1$
#1815000
b100011 *
b100011 6
14
b100011 )
b100011 9
17
b100011 (
b100011 +
b100011 .
b100011 1
b100011 <
1:
b11011 2
b11011 /
b11011 ,
1&
#1820000
0&
1%
#1825000
b100100 *
b100100 6
15
b100100 )
b100100 9
18
b100100 (
b100100 +
b100100 .
b100100 1
b100100 <
1;
b11100 ,
b11100 /
b11100 2
1&
#1830000
0&
0$
#1835000
04
07
0:
b11101 2
b11101 /
b11101 ,
1&
#1840000
0&
0%
#1845000
05
08
0;
b11110 ,
b11110 /
b11110 2
1&
#1850000
0&
1$
#1855000
b100101 *
b100101 6
14
b100101 )
b100101 9
17
b100101 (
b100101 +
b100101 .
b100101 1
b100101 <
1:
b11111 2
b11111 /
b11111 ,
1&
#1860000
0&
1%
#1865000
b100110 *
b100110 6
15
b100110 )
b100110 9
18
b100110 (
b100110 +
b100110 .
b100110 1
b100110 <
1;
b100000 ,
b100000 /
b100000 2
1&
#1870000
0&
0$
#1875000
04
07
0:
b100001 2
b100001 /
b100001 ,
1&
#1880000
0&
0%
#1885000
05
08
0;
b100010 ,
b100010 /
b100010 2
1&
#1890000
0&
1$
#1895000
b1000 3
b1000 0
b1000 -
b100111 *
b100111 6
14
b100111 )
b100111 9
17
b100111 (
b100111 +
b100111 .
b100111 1
b100111 <
1:
b100011 2
b100011 /
b100011 ,
1&
#1900000
0&
1%
#1905000
b101000 *
b101000 6
15
b101000 )
b101000 9
18
b101000 (
b101000 +
b101000 .
b101000 1
b101000 <
1;
b100100 ,
b100100 /
b100100 2
1&
#1910000
0&
0$
#1915000
04
07
0:
b100101 2
b100101 /
b100101 ,
1&
#1920000
0&
0%
#1925000
05
08
0;
b100110 ,
b100110 /
b100110 2
1&
#1930000
0&
1$
#1935000
b101001 *
b101001 6
14
b101001 )
b101001 9
17
b101001 (
b101001 +
b101001 .
b101001 1
b101001 <
1:
b100111 2
b100111 /
b100111 ,
1&
#1940000
0&
1%
#1945000
b101010 *
b101010 6
15
b101010 )
b101010 9
18
b101010 (
b101010 +
b101010 .
b101010 1
b101010 <
1;
b101000 ,
b101000 /
b101000 2
1&
#1950000
0&
0$
#1955000
04
07
0:
b101001 2
b101001 /
b101001 ,
1&
#1960000
0&
0%
#1965000
05
08
0;
b101010 ,
b101010 /
b101010 2
1&
#1970000
0&
1$
#1975000
b101011 *
b101011 6
14
b101011 )
b101011 9
17
b101011 (
b101011 +
b101011 .
b101011 1
b101011 <
1:
b101011 2
b101011 /
b101011 ,
1&
#1980000
0&
1%
#1985000
b1001 -
b1001 0
b1001 3
b101100 *
b101100 6
15
b101100 )
b101100 9
18
b101100 (
b101100 +
b101100 .
b101100 1
b101100 <
1;
b101100 ,
b101100 /
b101100 2
1&
#1990000
0&
0$
#1995000
04
07
0:
b101101 2
b101101 /
b101101 ,
1&
#2000000
0&
0%
#2005000
05
08
0;
b101110 ,
b101110 /
b101110 2
1&
#2010000
0&
1$
#2015000
b101101 *
b101101 6
14
b101101 )
b101101 9
17
b101101 (
b101101 +
b101101 .
b101101 1
b101101 <
1:
b101111 2
b101111 /
b101111 ,
1&
#2020000
0&
1%
#2025000
b101110 *
b101110 6
15
b101110 )
b101110 9
18
b101110 (
b101110 +
b101110 .
b101110 1
b101110 <
1;
b110000 ,
b110000 /
b110000 2
1&
#2030000
0&
0$
#2035000
04
07
0:
b110001 2
b110001 /
b110001 ,
1&
#2040000
0&
0%
#2045000
05
08
0;
b110010 ,
b110010 /
b110010 2
1&
#2050000
0&
1$
#2055000
b101111 *
b101111 6
14
b101111 )
b101111 9
17
b101111 (
b101111 +
b101111 .
b101111 1
b101111 <
1:
b0 2
b0 /
b0 ,
1&
#2060000
0&
1%
#2065000
b110000 *
b110000 6
15
b110000 )
b110000 9
18
b110000 (
b110000 +
b110000 .
b110000 1
b110000 <
1;
1#
b1 ,
1"
b1 /
1!
b1 2
1&
#2070000
0&
0$
#2075000
04
07
0:
b10 2
b10 /
b10 ,
1&
#2080000
0&
0%
#2085000
05
08
0;
b11 ,
b11 /
b11 2
1&
#2090000
0&
1$
#2095000
b1010 3
b1010 0
b1010 -
b110001 *
b110001 6
14
b110001 )
b110001 9
17
b110001 (
b110001 +
b110001 .
b110001 1
b110001 <
1:
b100 2
b100 /
b100 ,
1&
#2100000
0&
1%
#2105000
b110010 *
b110010 6
15
b110010 )
b110010 9
18
b110010 (
b110010 +
b110010 .
b110010 1
b110010 <
1;
b101 ,
b101 /
b101 2
1&
#2110000
0&
0$
#2115000
04
07
0:
b110 2
b110 /
b110 ,
1&
#2120000
0&
0%
#2125000
05
08
0;
b111 ,
b111 /
b111 2
1&
#2130000
0&
1$
#2135000
b110011 *
b110011 6
14
b110011 )
b110011 9
17
b110011 (
b110011 +
b110011 .
b110011 1
b110011 <
1:
b1000 2
b1000 /
b1000 ,
1&
#2140000
0&
1%
#2145000
b110100 *
b110100 6
15
b110100 )
b110100 9
18
b110100 (
b110100 +
b110100 .
b110100 1
b110100 <
1;
b1001 ,
b1001 /
b1001 2
1&
#2150000
0&
0$
#2155000
04
07
0:
b1010 2
b1010 /
b1010 ,
1&
#2160000
0&
0%
#2165000
05
08
0;
0#
b1011 ,
0"
b1011 /
0!
b1011 2
1&
#2170000
0&
1$
#2175000
b110101 *
b110101 6
14
b110101 )
b110101 9
17
b110101 (
b110101 +
b110101 .
b110101 1
b110101 <
1:
b1100 2
b1100 /
b1100 ,
1&
#2180000
0&
1%
#2185000
b1011 -
b1011 0
b1011 3
b110110 *
b110110 6
15
b110110 )
b110110 9
18
b110110 (
b110110 +
b110110 .
b110110 1
b110110 <
1;
b1101 ,
b1101 /
b1101 2
1&
#2190000
0&
0$
#2195000
04
07
0:
b1110 2
b1110 /
b1110 ,
1&
#2200000
0&
0%
