RGB_Mixer/pwm_driver.sv
module pwm_driver(
input wire clk,
input wire rst,
input wire [7:0] duty_cycle,
output reg pwm_out
);
reg [7:0] cycle;
reg [7:0] counter;


// Calculate cycle value
always @(duty_cycle) begin
    cycle = duty_cycle / 5.1; // Approximation of duty_cycle / 2.55
end

always @(posedge clk or posedge rst) begin 
    if (rst) begin 
        pwm_out <= 1'b0;
        counter <= 8'b0;
    end 
    else begin
        if (counter < 8'd50) 
            counter <= counter + 8'd1; 
        else 
            counter <= 8'd0; 

        pwm_out <= (counter < cycle) ? 1'b1 : 1'b0;
    end 
end 
endmodule

RGB_Mixer/rotary_encoder.sv
module rotary_encoder(

    input clk, rst,
    input A, B,
    output reg [7:0] count

);
    reg Aprev, Bprev;

    always_ff @( posedge clk or posedge rst ) begin : encoder
    
    if (rst) begin 
        Aprev <= 1'b0;
        Bprev <= 1'b0;
        count <= 0;
    end else begin 
        Aprev <= A;
        Bprev <= B;
        if (A && !Aprev) begin 
            count <= count + 1;
        end 
        if (B && !Bprev) begin 

            count  <= count - 1;
        end
    end 
    end    
endmodule

RGB_Mixer/led-driver.sv
module rgb_led_driver(
    input clk, rst,
    input blue_A, blue_B, red_A, red_B, green_A, green_B,
    output pwm_red, pwm_green, pwm_blue
);

    
    wire [7:0] red_counter;
    wire [7:0] green_counter;
    wire [7:0] blue_counter;
    
    rotary_encoder encoder_red (
        .clk(clk),
        .rst(rst),
        .A(red_A),
        .B(red_B),
        .count(red_counter)
    );

    pwm_driver driver_red (
        .clk(clk),
        .rst(rst),
        .duty_cycle(red_counter),
        .pwm_out(pwm_red)
    );

    rotary_encoder encoder_green (
        .clk(clk),
        .rst(rst),
        .A(green_A),
        .B(green_B),
        .count(green_counter)
    );

    pwm_driver driver_green (
        .clk(clk),
        .rst(rst),
        .duty_cycle(green_counter),
        .pwm_out(pwm_green)
    );

    rotary_encoder encoder_blue (
        .clk(clk),
        .rst(rst),
        .A(blue_A),
        .B(blue_B),
        .count(blue_counter)
    );

    pwm_driver driver_blue (
        .clk(clk),
        .rst(rst),
        .duty_cycle(blue_counter),
        .pwm_out(pwm_blue)
    );

    always @(posedge clk) begin
        $display("Red: %d, Green: %d, Blue: %d", red_counter, green_counter, blue_counter);
    end
endmodule

RGB_Mixer/led_driver_tb.sv
`timescale 1ns / 1ps

module led_driver_tb;

    reg clk;
    reg rst;

    reg blue_A; 
    reg blue_B; 

    reg red_A; 
    reg red_B;

    reg green_A; 
    reg green_B;

    wire pwm_red;
    wire pwm_green;
    wire pwm_blue;

    rgb_led_driver uut(
        .clk(clk),
        .rst(rst),
        .red_A(red_A),
        .red_B(red_B),
        .green_A(green_A),
        .green_B(green_B),
        .blue_A(blue_A),
        .blue_B(blue_B),
        .pwm_red(pwm_red),
        .pwm_blue(pwm_blue),
        .pwm_green(pwm_green)
    );

  // Clock generation
  always begin
    clk = 1'b0;
    #5;
    clk = 1'b1;
    #5;
  end



  initial begin
    // Initialize inputs
    rst = 1'b1;
    {red_A, red_B, green_A, green_B, blue_A, blue_B} = 6'b000000;

    // Reset
    #20 rst = 1'b0;

    // Test red at 25%, green at 50%, blue at 75%
    repeat(25) begin
        #10 red_A = 1'b1;
        #10 red_B = 1'b1;
        #10 red_A = 1'b0;
        #10 red_B = 1'b0;
    end

    repeat(64) begin
        #10 green_A = 1'b1;
        #10 green_B = 1'b1;
        #10 green_A = 1'b0;
        #10 green_B = 1'b0;
    end

    repeat(80) begin
        #10 blue_A = 1'b1;
        #10 blue_B = 1'b1;
        #10 blue_A = 1'b0;
        #10 blue_B = 1'b0;
    end

    #2000;

    // turning things down
    repeat(20) begin
        #10 red_B = 1'b1;
        #10 red_A = 1'b1;
        #10 red_B = 1'b0;
        #10 red_A = 1'b0;
    end

    repeat(30) begin
        #10 green_B = 1'b1;
        #10 green_A = 1'b1;
        #10 green_B = 1'b0;
        #10 green_A = 1'b0;
    end

    repeat(10) begin
        #10 blue_B = 1'b1;
        #10 blue_A = 1'b1;
        #10 blue_B = 1'b0;
        #10 blue_A = 1'b0;
    end

    #1000;

    #20 rst = 1'b1;
    #20 rst = 1'b0;

    #1000;
    // End simulation
    #100 $finish;
  end

  // VCD file generation
  initial begin
      $dumpfile("led_driver.vcd");
      $dumpvars(0, led_driver_tb);
  end


endmodule

RGB_Mixer/led_driver.vcd
$date
	Wed Oct 16 15:47:55 2024
$end
$version
	Icarus Verilog
$end
$timescale
	1ps
$end
$scope module led_driver_tb $end
$var wire 1 ! pwm_red $end
$var wire 1 " pwm_green $end
$var wire 1 # pwm_blue $end
$var reg 1 $ blue_A $end
$var reg 1 % blue_B $end
$var reg 1 & clk $end
$var reg 1 ' green_A $end
$var reg 1 ( green_B $end
$var reg 1 ) red_A $end
$var reg 1 * red_B $end
$var reg 1 + rst $end
$scope module uut $end
$var wire 1 $ blue_A $end
$var wire 1 % blue_B $end
$var wire 1 & clk $end
$var wire 1 ' green_A $end
$var wire 1 ( green_B $end
$var wire 1 ) red_A $end
$var wire 1 * red_B $end
$var wire 1 + rst $end
$var wire 8 , red_counter [7:0] $end
$var wire 1 ! pwm_red $end
$var wire 1 " pwm_green $end
$var wire 1 # pwm_blue $end
$var wire 8 - green_counter [7:0] $end
$var wire 8 . blue_counter [7:0] $end
$scope module driver_blue $end
$var wire 1 & clk $end
$var wire 1 + rst $end
$var wire 8 / duty_cycle [7:0] $end
$var reg 8 0 counter [7:0] $end
$var reg 8 1 cycle [7:0] $end
$var reg 1 # pwm_out $end
$upscope $end
$scope module driver_green $end
$var wire 1 & clk $end
$var wire 1 + rst $end
$var wire 8 2 duty_cycle [7:0] $end
$var reg 8 3 counter [7:0] $end
$var reg 8 4 cycle [7:0] $end
$var reg 1 " pwm_out $end
$upscope $end
$scope module driver_red $end
$var wire 1 & clk $end
$var wire 1 + rst $end
$var wire 8 5 duty_cycle [7:0] $end
$var reg 8 6 counter [7:0] $end
$var reg 8 7 cycle [7:0] $end
$var reg 1 ! pwm_out $end
$upscope $end
$scope module encoder_blue $end
$var wire 1 $ A $end
$var wire 1 % B $end
$var wire 1 & clk $end
$var wire 1 + rst $end
$var reg 1 8 Aprev $end
$var reg 1 9 Bprev $end
$var reg 8 : count [7:0] $end
$scope begin encoder $end
$upscope $end
$upscope $end
$scope module encoder_green $end
$var wire 1 ' A $end
$var wire 1 ( B $end
$var wire 1 & clk $end
$var wire 1 + rst $end
$var reg 1 ; Aprev $end
$var reg 1 < Bprev $end
$var reg 8 = count [7:0] $end
$scope begin encoder $end
$upscope $end
$upscope $end
$scope module encoder_red $end
$var wire 1 ) A $end
$var wire 1 * B $end
$var wire 1 & clk $end
$var wire 1 + rst $end
$var reg 1 > Aprev $end
$var reg 1 ? Bprev $end
$var reg 8 @ count [7:0] $end
$scope begin encoder $end
$upscope $end
$upscope $end
$upscope $end
$upscope $end
$enddefinitions $end
$comment Show the parameter values. $end
$dumpall
$end
#0
$dumpvars
b0 @
0?
0>
b0 =
0<
0;
b0 :
09
08
b0 7
b0 6
b0 5
b0 4
b0 3
b0 2
b0 1
b0 0
b0 /
b0 .
b0 -
b0 ,
1+
0*
0)
0(
0'
0&
0%
0$
0#
0"
0!
$end
#5000
1&
#10000
0&
#15000
1&
#20000
0&
0+
#25000
b1 0
b1 3
b1 6
1&
#30000
0&
1)
#35000
b1 ,
b1 5
b1 @
1>
b10 6
b10 3
b10 0
1&
#40000
0&
1*
#45000
b10 ,
b10 5
b10 @
1?
b11 0
b11 3
b11 6
1&
#50000
0&
0)
#55000
0>
b100 6
b100 3
b100 0
1&
#60000
0&
0*
#65000
0?
b101 0
b101 3
b101 6
1&
#70000
0&
1)
#75000
b1 7
b11 ,
b11 5
b11 @
1>
b110 6
b110 3
b110 0
1&
#80000
0&
1*
#85000
b100 ,
b100 5
b100 @
1?
b111 0
b111 3
b111 6
1&
#90000
0&
0)
#95000
0>
b1000 6
b1000 3
b1000 0
1&
#100000
0&
0*
#105000
0?
b1001 0
b1001 3
b1001 6
1&
#110000
0&
1)
#115000
b101 ,
b101 5
b101 @
1>
b1010 6
b1010 3
b1010 0
1&
#120000
0&
1*
#125000
b110 ,
b110 5
b110 @
1?
b1011 0
b1011 3
b1011 6
1&
#130000
0&
0)
#135000
0>
b1100 6
b1100 3
b1100 0
1&
#140000
0&
0*
#145000
0?
b1101 0
b1101 3
b1101 6
1&
#150000
0&
1)
#155000
b111 ,
b111 5
b111 @
1>
b1110 6
b1110 3
b1110 0
1&
#160000
0&
1*
#165000
b10 7
b1000 ,
b1000 5
b1000 @
1?
b1111 0
b1111 3
b1111 6
1&
#170000
0&
0)
#175000
0>
b10000 6
b10000 3
b10000 0
1&
#180000
0&
0*
#185000
0?
b10001 0
b10001 3
b10001 6
1&
#190000
0&
1)
#195000
b1001 ,
b1001 5
b1001 @
1>
b10010 6
b10010 3
b10010 0
1&
#200000
0&
1*
#205000
b1010 ,
b1010 5
b1010 @
1?
b10011 0
b10011 3
b10011 6
1&
#210000
0&
0)
#215000
0>
b10100 6
b10100 3
b10100 0
1&
#220000
0&
0*
#225000
0?
b10101 0
b10101 3
b10101 6
1&
#230000
0&
1)
#235000
b1011 ,
b1011 5
b1011 @
1>
b10110 6
b10110 3
b10110 0
1&
#240000
0&
1*
#245000
b1100 ,
b1100 5
b1100 @
1?
b10111 0
b10111 3
b10111 6
1&
#250000
0&
0)
#255000
0>
b11000 6
b11000 3
b11000 0
1&
#260000
0&
0*
#265000
0?
b11001 0
b11001 3
b11001 6
1&
#270000
0&
1)
#275000
b11 7
b1101 ,
b1101 5
b1101 @
1>
b11010 6
b11010 3
b11010 0
1&
#280000
0&
1*
#285000
b1110 ,
b1110 5
b1110 @
1?
b11011 0
b11011 3
b11011 6
1&
#290000
0&
0)
#295000
0>
b11100 6
b11100 3
b11100 0
1&
#300000
0&
0*
#305000
0?
b11101 0
b11101 3
b11101 6
1&
#310000
0&
1)
#315000
b1111 ,
b1111 5
b1111 @
1>
b11110 6
b11110 3
b11110 0
1&
#320000
0&
1*
#325000
b10000 ,
b10000 5
b10000 @
1?
b11111 0
b11111 3
b11111 6
1&
#330000
0&
0)
#335000
0>
b100000 6
b100000 3
b100000 0
1&
#340000
0&
0*
#345000
0?
b100001 0
b100001 3
b100001 6
1&
#350000
0&
1)
#355000
b10001 ,
b10001 5
b10001 @
1>
b100010 6
b100010 3
b100010 0
1&
#360000
0&
1*
#365000
b100 7
b10010 ,
b10010 5
b10010 @
1?
b100011 0
b100011 3
b100011 6
1&
#370000
0&
0)
#375000
0>
b100100 6
b100100 3
b100100 0
1&
#380000
0&
0*
#385000
0?
b100101 0
b100101 3
b100101 6
1&
#390000
0&
1)
#395000
b10011 ,
b10011 5
b10011 @
1>
b100110 6
b100110 3
b100110 0
1&
#400000
0&
1*
#405000
b10100 ,
b10100 5
b10100 @
1?
b100111 0
b100111 3
b100111 6
1&
#410000
0&
0)
#415000
0>
b101000 6
b101000 3
b101000 0
1&
#420000
0&
0*
#425000
0?
b101001 0
b101001 3
b101001 6
1&
#430000
0&
1)
#435000
b10101 ,
b10101 5
b10101 @
1>
b101010 6
b101010 3
b101010 0
1&
#440000
0&
1*
#445000
b10110 ,
b10110 5
b10110 @
1?
b101011 0
b101011 3
b101011 6
1&
#450000
0&
0)
#455000
0>
b101100 6
b101100 3
b101100 0
1&
#460000
0&
0*
#465000
0?
b101101 0
b101101 3
b101101 6
1&
#470000
0&
1)
#475000
b101 7
b10111 ,
b10111 5
b10111 @
1>
b101110 6
b101110 3
b101110 0
1&
#480000
0&
1*
#485000
b11000 ,
b11000 5
b11000 @
1?
b101111 0
b101111 3
b101111 6
1&
#490000
0&
0)
#495000
0>
b110000 6
b110000 3
b110000 0
1&
#500000
0&
0*
#505000
0?
b110001 0
b110001 3
b110001 6
1&
#510000
0&
1)
#515000
b11001 ,
b11001 5
b11001 @
1>
b110010 6
b110010 3
b110010 0
1&
#520000
0&
1*
#525000
b11010 ,
b11010 5
b11010 @
1?
b0 0
b0 3
b0 6
1&
#530000
0&
0)
#535000
0>
1!
b1 6
b1 3
b1 0
1&
#540000
0&
0*
#545000
0?
b10 0
b10 3
b10 6
1&
#550000
0&
1)
#555000
b11011 ,
b11011 5
b11011 @
1>
b11 6
b11 3
b11 0
1&
#560000
0&
1*
#565000
b11100 ,
b11100 5
b11100 @
1?
b100 0
b100 3
b100 6
1&
#570000
0&
0)
#575000
0>
b101 6
b101 3
b101 0
1&
#580000
0&
0*
#585000
0?
b110 0
b110 3
0!
b110 6
1&
#590000
0&
1)
#595000
b110 7
b11101 ,
b11101 5
b11101 @
1>
b111 6
b111 3
b111 0
1&
#600000
0&
1*
#605000
b11110 ,
b11110 5
b11110 @
1?
b1000 0
b1000 3
b1000 6
1&
#610000
0&
0)
#615000
0>
b1001 6
b1001 3
b1001 0
1&
#620000
0&
0*
#625000
0?
b1010 0
b1010 3
b1010 6
1&
#630000
0&
1)
#635000
b11111 ,
b11111 5
b11111 @
1>
b1011 6
b1011 3
b1011 0
1&
#640000
0&
1*
#645000
b100000 ,
b100000 5
b100000 @
1?
b1100 0
b1100 3
b1100 6
1&
#650000
0&
0)
#655000
0>
b1101 6
b1101 3
b1101 0
1&
#660000
0&
0*
#665000
0?
b1110 0
b1110 3
b1110 6
1&
#670000
0&
1)
#675000
b100001 ,
b100001 5
b100001 @
1>
b1111 6
b1111 3
b1111 0
1&
#680000
0&
1*
#685000
b111 7
b100010 ,
b100010 5
b100010 @
1?
b10000 0
b10000 3
b10000 6
1&
#690000
0&
0)
#695000
0>
b10001 6
b10001 3
b10001 0
1&
#700000
0&
0*
#705000
0?
b10010 0
b10010 3
b10010 6
1&
#710000
0&
1)
#715000
b100011 ,
b100011 5
b100011 @
1>
b10011 6
b10011 3
b10011 0
1&
#720000
0&
1*
#725000
b100100 ,
b100100 5
b100100 @
1?
b10100 0
b10100 3
b10100 6
1&
#730000
0&
0)
#735000
0>
b10101 6
b10101 3
b10101 0
1&
#740000
0&
0*
#745000
0?
b10110 0
b10110 3
b10110 6
1&
#750000
0&
1)
#755000
b100101 ,
b100101 5
b100101 @
1>
b10111 6
b10111 3
b10111 0
1&
#760000
0&
1*
#765000
b100110 ,
b100110 5
b100110 @
1?
b11000 0
b11000 3
b11000 6
1&
#770000
0&
0)
#775000
0>
b11001 6
b11001 3
b11001 0
1&
#780000
0&
0*
#785000
0?
b11010 0
b11010 3
b11010 6
1&
#790000
0&
1)
#795000
b1000 7
b100111 ,
b100111 5
b100111 @
1>
b11011 6
b11011 3
b11011 0
1&
#800000
0&
1*
#805000
b101000 ,
b101000 5
b101000 @
1?
b11100 0
b11100 3
b11100 6
1&
#810000
0&
0)
#815000
0>
b11101 6
b11101 3
b11101 0
1&
#820000
0&
0*
#825000
0?
b11110 0
b11110 3
b11110 6
1&
#830000
0&
1)
#835000
b101001 ,
b101001 5
b101001 @
1>
b11111 6
b11111 3
b11111 0
1&
#840000
0&
1*
#845000
b101010 ,
b101010 5
b101010 @
1?
b100000 0
b100000 3
b100000 6
1&
#850000
0&
0)
#855000
0>
b100001 6
b100001 3
b100001 0
1&
#860000
0&
0*
#865000
0?
b100010 0
b100010 3
b100010 6
1&
#870000
0&
1)
#875000
b101011 ,
b101011 5
b101011 @
1>
b100011 6
b100011 3
b100011 0
1&
#880000
0&
1*
#885000
b1001 7
b101100 ,
b101100 5
b101100 @
1?
b100100 0
b100100 3
b100100 6
1&
#890000
0&
0)
#895000
0>
b100101 6
b100101 3
b100101 0
1&
#900000
0&
0*
#905000
0?
b100110 0
b100110 3
b100110 6
1&
#910000
0&
1)
#915000
b101101 ,
b101101 5
b101101 @
1>
b100111 6
b100111 3
b100111 0
1&
#920000
0&
1*
#925000
b101110 ,
b101110 5
b101110 @
1?
b101000 0
b101000 3
b101000 6
1&
#930000
0&
0)
#935000
0>
b101001 6
b101001 3
b101001 0
1&
#940000
0&
0*
#945000
0?
b101010 0
b101010 3
b101010 6
1&
#950000
0&
1)
#955000
b101111 ,
b101111 5
b101111 @
1>
b101011 6
b101011 3
b101011 0
1&
#960000
0&
1*
#965000
b110000 ,
b110000 5
b110000 @
1?
b101100 0
b101100 3
b101100 6
1&
#970000
0&
0)
#975000
0>
b101101 6
b101101 3
b101101 0
1&
#980000
0&
0*
#985000
0?
b101110 0
b101110 3
b101110 6
1&
#990000
0&
1)
#995000
b1010 7
b110001 ,
b110001 5
b110001 @
1>
b101111 6
b101111 3
b101111 0
1&
#1000000
0&
1*
#1005000
b110010 ,
b110010 5
b110010 @
1?
b110000 0
b110000 3
b110000 6
1&
#1010000
0&
0)
#1015000
0>
b110001 6
b110001 3
b110001 0
1&
#1020000
0&
0*
#1025000
0?
b110010 0
b110010 3
b110010 6
1&
#1030000
0&
1'
#1035000
b1 -
b1 2
b1 =
1;
b0 6
b0 3
b0 0
1&
#1040000
0&
1(
#1045000
b10 -
b10 2
b10 =
1<
b1 0
b1 3
1!
b1 6
1&
#1050000
0&
0'
#1055000
0;
b10 6
b10 3
b10 0
1&
#1060000
0&
0(
#1065000
0<
b11 0
b11 3
b11 6
1&
#1070000
0&
1'
#1075000
b1 4
b11 -
b11 2
b11 =
1;
b100 6
b100 3
b100 0
1&
#1080000
0&
1(
#1085000
b100 -
b100 2
b100 =
1<
b101 0
b101 3
b101 6
1&
#1090000
0&
0'
#1095000
0;
b110 6
b110 3
b110 0
1&
#1100000
0&
0(
#1105000
0<
b111 0
b111 3
b111 6
1&
#1110000
0&
1'
#1115000
b101 -
b101 2
b101 =
1;
b1000 6
b1000 3
b1000 0
1&
#1120000
0&
1(
#1125000
b110 -
b110 2
b110 =
1<
b1001 0
b1001 3
b1001 6
1&
#1130000
0&
0'
#1135000
0;
b1010 6
b1010 3
b1010 0
1&
#1140000
0&
0(
#1145000
0<
b1011 0
b1011 3
0!
b1011 6
1&
#1150000
0&
1'
#1155000
b111 -
b111 2
b111 =
1;
b1100 6
b1100 3
b1100 0
1&
#1160000
0&
1(
#1165000
b10 4
b1000 -
b1000 2
b1000 =
1<
b1101 0
b1101 3
b1101 6
1&
#1170000
0&
0'
#1175000
0;
b1110 6
b1110 3
b1110 0
1&
#1180000
0&
0(
#1185000
0<
b1111 0
b1111 3
b1111 6
1&
#1190000
0&
1'
#1195000
b1001 -
b1001 2
b1001 =
1;
b10000 6
b10000 3
b10000 0
1&
#1200000
0&
1(
#1205000
b1010 -
b1010 2
b1010 =
1<
b10001 0
b10001 3
b10001 6
1&
#1210000
0&
0'
#1215000
0;
b10010 6
b10010 3
b10010 0
1&
#1220000
0&
0(
#1225000
0<
b10011 0
b10011 3
b10011 6
1&
#1230000
0&
1'
#1235000
b1011 -
b1011 2
b1011 =
1;
b10100 6
b10100 3
b10100 0
1&
#1240000
0&
1(
#1245000
b1100 -
b1100 2
b1100 =
1<
b10101 0
b10101 3
b10101 6
1&
#1250000
0&
0'
#1255000
0;
b10110 6
b10110 3
b10110 0
1&
#1260000
0&
0(
#1265000
0<
b10111 0
b10111 3
b10111 6
1&
#1270000
0&
1'
#1275000
b11 4
b1101 -
b1101 2
b1101 =
1;
b11000 6
b11000 3
b11000 0
1&
#1280000
0&
1(
#1285000
b1110 -
b1110 2
b1110 =
1<
b11001 0
b11001 3
b11001 6
1&
#1290000
0&
0'
#1295000
0;
b11010 6
b11010 3
b11010 0
1&
#1300000
0&
0(
#1305000
0<
b11011 0
b11011 3
b11011 6
1&
#1310000
0&
1'
#1315000
b1111 -
b1111 2
b1111 =
1;
b11100 6
b11100 3
b11100 0
1&
#1320000
0&
1(
#1325000
b10000 -
b10000 2
b10000 =
1<
b11101 0
b11101 3
b11101 6
1&
#1330000
0&
0'
#1335000
0;
b11110 6
b11110 3
b11110 0
1&
#1340000
0&
0(
#1345000
0<
b11111 0
b11111 3
b11111 6
1&
#1350000
0&
1'
#1355000
b10001 -
b10001 2
b10001 =
1;
b100000 6
b100000 3
b100000 0
1&
#1360000
0&
1(
#1365000
b100 4
b10010 -
b10010 2
b10010 =
1<
b100001 0
b100001 3
b100001 6
1&
#1370000
0&
0'
#1375000
0;
b100010 6
b100010 3
b100010 0
1&
#1380000
0&
0(
#1385000
0<
b100011 0
b100011 3
b100011 6
1&
#1390000
0&
1'
#1395000
b10011 -
b10011 2
b10011 =
1;
b100100 6
b100100 3
b100100 0
1&
#1400000
0&
1(
#1405000
b10100 -
b10100 2
b10100 =
1<
b100101 0
b100101 3
b100101 6
1&
#1410000
0&
0'
#1415000
0;
b100110 6
b100110 3
b100110 0
1&
#1420000
0&
0(
#1425000
0<
b100111 0
b100111 3
b100111 6
1&
#1430000
0&
1'
#1435000
b10101 -
b10101 2
b10101 =
1;
b101000 6
b101000 3
b101000 0
1&
#1440000
0&
1(
#1445000
b10110 -
b10110 2
b10110 =
1<
b101001 0
b101001 3
b101001 6
1&
#1450000
0&
0'
#1455000
0;
b101010 6
b101010 3
b101010 0
1&
#1460000
0&
0(
#1465000
0<
b101011 0
b101011 3
b101011 6
1&
#1470000
0&
1'
#1475000
b101 4
b10111 -
b10111 2
b10111 =
1;
b101100 6
b101100 3
b101100 0
1&
#1480000
0&
1(
#1485000
b11000 -
b11000 2
b11000 =
1<
b101101 0
b101101 3
b101101 6
1&
#1490000
0&
0'
#1495000
0;
b101110 6
b101110 3
b101110 0
1&
#1500000
0&
0(
#1505000
0<
b101111 0
b101111 3
b101111 6
1&
#1510000
0&
1'
#1515000
b11001 -
b11001 2
b11001 =
1;
b110000 6
b110000 3
b110000 0
1&
#1520000
0&
1(
#1525000
b11010 -
b11010 2
b11010 =
1<
b110001 0
b110001 3
b110001 6
1&
#1530000
0&
0'
#1535000
0;
b110010 6
b110010 3
b110010 0
1&
#1540000
0&
0(
#1545000
0<
b0 0
b0 3
b0 6
1&
#1550000
0&
1'
#1555000
b11011 -
b11011 2
b11011 =
1;
1!
b1 6
1"
b1 3
b1 0
1&
#1560000
0&
1(
#1565000
b11100 -
b11100 2
b11100 =
1<
b10 0
b10 3
b10 6
1&
#1570000
0&
0'
#1575000
0;
b11 6
b11 3
b11 0
1&
#1580000
0&
0(
#1585000
0<
b100 0
b100 3
b100 6
1&
#1590000
0&
1'
#1595000
b110 4
b11101 -
b11101 2
b11101 =
1;
b101 6
b101 3
b101 0
1&
#1600000
0&
1(
#1605000
b11110 -
b11110 2
b11110 =
1<
b110 0
b110 3
b110 6
1&
#1610000
0&
0'
#1615000
0;
b111 6
0"
b111 3
b111 0
1&
#1620000
0&
0(
#1625000
0<
b1000 0
b1000 3
b1000 6
1&
#1630000
0&
1'
#1635000
b11111 -
b11111 2
b11111 =
1;
b1001 6
b1001 3
b1001 0
1&
#1640000
0&
1(
#1645000
b100000 -
b100000 2
b100000 =
1<
b1010 0
b1010 3
b1010 6
1&
#1650000
0&
0'
#1655000
0;
0!
b1011 6
b1011 3
b1011 0
1&
#1660000
0&
0(
#1665000
0<
b1100 0
b1100 3
b1100 6
1&
#1670000
0&
1'
#1675000
b100001 -
b100001 2
b100001 =
1;
b1101 6
b1101 3
b1101 0
1&
#1680000
0&
1(
#1685000
b111 4
b100010 -
b100010 2
b100010 =
1<
b1110 0
b1110 3
b1110 6
1&
#1690000
0&
0'
#1695000
0;
b1111 6
b1111 3
b1111 0
1&
#1700000
0&
0(
#1705000
0<
b10000 0
b10000 3
b10000 6
1&
#1710000
0&
1'
#1715000
b100011 -
b100011 2
b100011 =
1;
b10001 6
b10001 3
b10001 0
1&
#1720000
0&
1(
#1725000
b100100 -
b100100 2
b100100 =
1<
b10010 0
b10010 3
b10010 6
1&
#1730000
0&
0'
#1735000
0;
b10011 6
b10011 3
b10011 0
1&
#1740000
0&
0(
#1745000
0<
b10100 0
b10100 3
b10100 6
1&
#1750000
0&
1'
#1755000
b100101 -
b100101 2
b100101 =
1;
b10101 6
b10101 3
b10101 0
1&
#1760000
0&
1(
#1765000
b100110 -
b100110 2
b100110 =
1<
b10110 0
b10110 3
b10110 6
1&
#1770000
0&
0'
#1775000
0;
b10111 6
b10111 3
b10111 0
1&
#1780000
0&
0(
#1785000
0<
b11000 0
b11000 3
b11000 6
1&
#1790000
0&
1'
#1795000
b1000 4
b100111 -
b100111 2
b100111 =
1;
b11001 6
b11001 3
b11001 0
1&
#1800000
0&
1(
#1805000
b101000 -
b101000 2
b101000 =
1<
b11010 0
b11010 3
b11010 6
1&
#1810000
0&
0'
#1815000
0;
b11011 6
b11011 3
b11011 0
1&
#1820000
0&
0(
#1825000
0<
b11100 0
b11100 3
b11100 6
1&
#1830000
0&
1'
#1835000
b101001 -
b101001 2
b101001 =
1;
b11101 6
b11101 3
b11101 0
1&
#1840000
0&
1(
#1845000
b101010 -
b101010 2
b101010 =
1<
b11110 0
b11110 3
b11110 6
1&
#1850000
0&
0'
#1855000
0;
b11111 6
b11111 3
b11111 0
1&
#1860000
0&
0(
#1865000
0<
b100000 0
b100000 3
b100000 6
1&
#1870000
0&
1'
#1875000
b101011 -
b101011 2
b101011 =
1;
b100001 6
b100001 3
b100001 0
1&
#1880000
0&
1(
#1885000
b1001 4
b101100 -
b101100 2
b101100 =
1<
b100010 0
b100010 3
b100010 6
1&
#1890000
0&
0'
#1895000
0;
b100011 6
b100011 3
b100011 0
1&
#1900000
0&
0(
#1905000
0<
b100100 0
b100100 3
b100100 6
1&
#1910000
0&
1'
#1915000
b101101 -
b101101 2
b101101 =
1;
b100101 6
b100101 3
b100101 0
1&
#1920000
0&
1(
#1925000
b101110 -
b101110 2
b101110 =
1<
b100110 0
b100110 3
b100110 6
1&
#1930000
0&
0'
#1935000
0;
b100111 6
b100111 3
b100111 0
1&
#1940000
0&
0(
#1945000
0<
b101000 0
b101000 3
b101000 6
1&
#1950000
0&
1'
#1955000
b101111 -
b101111 2
b101111 =
1;
b101001 6
b101001 3
b101001 0
1&
#1960000
0&
1(
#1965000
b110000 -
b110000 2
b110000 =
1<
b101010 0
b101010 3
b101010 6
1&
#1970000
0&
0'
#1975000
0;
b101011 6
b101011 3
b101011 0
1&
#1980000
0&
0(
#1985000
0<
b101100 0
b101100 3
b101100 6
1&
#1990000
0&
1'
#1995000
b1010 4
b110001 -
b110001 2
b110001 =
1;
b101101 6
b101101 3
b101101 0
1&
#2000000
0&
1(
#2005000
b110010 -
b110010 2
b110010 =
1<
b101110 0
b101110 3
b101110 6
1&
#2010000
0&
0'
#2015000
0;
b101111 6
b101111 3
b101111 0
1&
#2020000
0&
0(
#2025000
0<
b110000 0
b110000 3
b110000 6
1&
#2030000
0&
1'
#2035000
b110011 -
b110011 2
b110011 =
1;
b110001 6
b110001 3
b110001 0
1&
#2040000
0&
1(
#2045000
b110100 -
b110100 2
b110100 =
1<
b110010 0
b110010 3
b110010 6
1&
#2050000
0&
0'
#2055000
0;
b0 6
b0 3
b0 0
1&
#2060000
0&
0(
#2065000
0<
b1 0
1"
b1 3
1!
b1 6
1&
#2070000
0&
1'
#2075000
b110101 -
b110101 2
b110101 =
1;
b10 6
b10 3
b10 0
1&
#2080000
0&
1(
#2085000
b1011 4
b110110 -
b110110 2
b110110 =
1<
b11 0
b11 3
b11 6
1&
#2090000
0&
0'
#2095000
0;
b100 6
b100 3
b100 0
1&
#2100000
0&
0(
#2105000
0<
b101 0
b101 3
b101 6
1&
#2110000
0&
1'
#2115000
b110111 -
b110111 2
b110111 =
1;
b110 6
b110 3
b110 0
1&
#2120000
0&
1(
#2125000
b111000 -
b111000 2
b111000 =
1<
b111 0
b111 3
b111 6
1&
#2130000
0&
0'
#2135000
0;
b1000 6
b1000 3
b1000 0
1&
#2140000
0&
0(
#2145000
0<
b1001 0
b1001 3
b1001 6
1&
#2150000
0&
1'
#2155000
b111001 -
b111001 2
b111001 =
1;
b1010 6
b1010 3
b1010 0
1&
#2160000
0&
1(
#2165000
b111010 -
b111010 2
b111010 =
1<
b1011 0
b1011 3
0!
b1011 6
1&
#2170000
0&
0'
#2175000
0;
b1100 6
0"
b1100 3
b1100 0
1&
#2180000
0&
0(
#2185000
0<
b1101 0
b1101 3
b1101 6
1&
#2190000
0&
1'
#2195000
b1100 4
b111011 -
b111011 2
b111011 =
1;
b1110 6
b1110 3
b1110 0
1&
#2200000
0&
1(
#2205000
b111100 -
b111100 2
b111100 =
1<
b1111 0
b1111 3
b1111 6
1&
#2210000
0&
0'
#2215000
0;
b10000 6
b10000 3
b10000 0
1&
#2220000
0&
0(
#2225000
0<
b10001 0
b10001 3
b10001 6
1&
#2230000
0&
1'
#2235000
b111101 -
b111101 2
b111101 =
1;
b10010 6
b10010 3
b10010 0
1&
#2240000
0&
1(
#2245000
b111110 -
b111110 2
b111110 =
1<
b10011 0
b10011 3
b10011 6
1&
#2250000
0&
0'
#2255000
0;
b10100 6
b10100 3
b10100 0
1&
#2260000
0&
0(
#2265000
0<
b10101 0
b10101 3
b10101 6
1&
#2270000
0&
1'
#2275000
b111111 -
b111111 2
b111111 =
1;
b10110 6
b10110 3
b10110 0
1&
#2280000
0&
1(
#2285000
b1101 4
b1000000 -
b1000000 2
b1000000 =
1<
b10111 0
b10111 3
b10111 6
1&
#2290000
0&
0'
#2295000
0;
b11000 6
b11000 3
b11000 0
1&
#2300000
0&
0(
#2305000
0<
b11001 0
b11001 3
b11001 6
1&
#2310000
0&
1'
#2315000
b1000001 -
b1000001 2
b1000001 =
1;
b11010 6
b11010 3
b11010 0
1&
#2320000
0&
1(
#2325000
b1000010 -
b1000010 2
b1000010 =
1<
b11011 0
b11011 3
b11011 6
1&
#2330000
0&
0'
#2335000
0;
b11100 6
b11100 3
b11100 0
1&
#2340000
0&
0(
#2345000
0<
b11101 0
b11101 3
b11101 6
1&
#2350000
0&
1'
#2355000
b1000011 -
b1000011 2
b1000011 =
1;
b11110 6
b11110 3
b11110 0
1&
#2360000
0&
1(
