systolic_array/block.v
module block (
    input clk,
    input wire rst,
    input [15:0] west_input, //inputs from the west
    input [15:0] north_input, // inputs from the north
    
    output reg [31:0] out_south, out_east, out  
);
    reg [31:0] product; // temp var to hold product


   always @(posedge clk or posedge rst) begin
    if (rst) begin   // reset
        out <= 32'b0;
        product <= 32'b0;
    end
    else begin
        product = west_input * north_input;  
        out <= out + product;
        out_south <= north_input;
        out_east <=  west_input;
    end  
   end 

endmodule


`timescale 1ns / 1ps

module block_tb();

    reg [15:0] north_input, west_input;
    reg rst;
    reg clk;

    wire [31:0] out_south, out_east, out;

    block uut(
        .north_input(north_input),
        .west_input(west_input),
        .out_east(out_east),
        .out_south(out_south),
        .out(out),
        .rst(rst),
        .clk(clk)
    );
   
    // Clock generation
    always begin
        #5 clk = ~clk; // Generate a 100MHz clock
    end

    // Test stimulus
    initial begin
        // Initialize signals
        clk = 0;
        rst = 1;
        north_input = 0;
        west_input = 0;

        // Dump waveforms
        $dumpfile("block_tb.vcd");
        $dumpvars(0, block_tb);

        // Reset sequence
        #20 rst = 0;

        // Test case 1: Simple multiplication
        #10 north_input = 16'd2; west_input = 16'd4;
        //#10 $display("Test case 1: north_input=%d, west_input=%d, out=%d", north_input, west_input,out);

        // Test case 2: Larger numbers
        #10 north_input = 16'd100; west_input = 16'd200;
        //#10 $display("Test case 2: north_input=%d, west_input=%d, out=%d", north_input, west_input, out);

        // Test case 3: Accumulation
        #10 north_input = 16'd3; west_input = 16'd5;
        //#10 $display("Test case 3: north_input=%d, west_input=%d, out=%d", north_input, west_input, out);

        // Test case 4: Reset during operation
        #10 north_input = 16'd10; west_input = 16'd10;
        #5 rst = 1;
        #5 rst = 0;
        //#10 $display("Test case 4 (after reset): north_input=%d, west_input=%d, out=%d", north_input, west_input, out);

        // End simulation
        #20 $finish;
    end

endmodule

block_tb.vcd
$date
	Mon Sep 30 11:34:27 2024
$end
$version
	Icarus Verilog
$end
$timescale
	1ps
$end
$scope module block_tb $end
$var wire 32 ! out_south [31:0] $end
$var wire 32 " out_east [31:0] $end
$var wire 32 # out [31:0] $end
$var reg 1 $ clk $end
$var reg 16 % north_input [15:0] $end
$var reg 1 & rst $end
$var reg 16 ' west_input [15:0] $end
$scope module uut $end
$var wire 1 $ clk $end
$var wire 16 ( north_input [15:0] $end
$var wire 1 & rst $end
$var wire 16 ) west_input [15:0] $end
$var reg 32 * out [31:0] $end
$var reg 32 + out_east [31:0] $end
$var reg 32 , out_south [31:0] $end
$var reg 32 - product [31:0] $end
$upscope $end
$upscope $end
$enddefinitions $end
$comment Show the parameter values. $end
$dumpall
$end
#0
$dumpvars
b0 -
bx ,
bx +
b0 *
b0 )
b0 (
b0 '
1&
b0 %
0$
b0 #
bx "
bx !
$end
#5000
1$
#10000
0$
#15000
1$
#20000
0$
0&
#25000
b0 "
b0 +
b0 !
b0 ,
1$
#30000
0$
b100 '
b100 )
b10 %
b10 (
#35000
b100 "
b100 +
b10 !
b10 ,
b1000 #
b1000 *
b1000 -
1$
#40000
0$
b11001000 '
b11001000 )
b1100100 %
b1100100 (
#45000
b11001000 "
b11001000 +
b1100100 !
b1100100 ,
b100111000101000 #
b100111000101000 *
b100111000100000 -
1$
#50000
0$
b101 '
b101 )
b11 %
b11 (
#55000
b101 "
b101 +
b11 !
b11 ,
b100111000110111 #
b100111000110111 *
b1111 -
1$
#60000
0$
b1010 '
b1010 )
b1010 %
b1010 (
#65000
b0 -
b0 #
b0 *
1$
1&
#70000
0$
0&
#75000
b1010 "
b1010 +
b1010 !
b1010 ,
b1100100 #
b1100100 *
b1100100 -
1$
#80000
0$
#85000
b11001000 #
b11001000 *
1$
