counter_tb.v
`timescale 1ns/1ps

module counter(
    input clk,
    input reset,
    output reg [3:0] count
);
    always @(posedge clk or posedge reset) begin
        if (reset)
            count <= 4'b0000;
        else
            count <= count + 1;
    end
endmodule

module counter_tb;
    reg clk;
    reg reset;
    wire [3:0] count;

    // Instantiate the Unit Under Test (UUT)
    counter uut (
        .clk(clk), 
        .reset(reset), 
        .count(count)
    );

    // Clock generation
    initial begin
        clk = 0;
        forever #5 clk = ~clk;
    end

    // Stimulus
    initial begin
        // Initialize Inputs
        reset = 1;

        // Wait 100 ns for global reset to finish
        #100;
        reset = 0;

        // Wait for a few clock cycles
        #100;

        // Finish the simulation
        $finish;
    end

    // Monitor
    initial begin
        $monitor("Time = %0t, Reset = %b, Count = %b", $time, reset, count);
    end

    // Optional: Generate VCD file for waveform viewing
    initial begin
        $dumpfile("counter_tb.vcd");
        $dumpvars(0, counter_tb);
    end
endmodule

counter_tb.vcd
$date
	Mon Sep 23 15:23:46 2024
$end
$version
	Icarus Verilog
$end
$timescale
	1ps
$end
$scope module counter_tb $end
$var wire 4 ! count [3:0] $end
$var reg 1 " clk $end
$var reg 1 # reset $end
$scope module uut $end
$var wire 1 " clk $end
$var wire 1 # reset $end
$var reg 4 $ count [3:0] $end
$upscope $end
$upscope $end
$enddefinitions $end
$comment Show the parameter values. $end
$dumpall
$end
#0
$dumpvars
b0 $
1#
0"
b0 !
$end
#5000
1"
#10000
0"
#15000
1"
#20000
0"
#25000
1"
#30000
0"
#35000
1"
#40000
0"
#45000
1"
#50000
0"
#55000
1"
#60000
0"
#65000
1"
#70000
0"
#75000
1"
#80000
0"
#85000
1"
#90000
0"
#95000
1"
#100000
0"
0#
#105000
b1 !
b1 $
1"
#110000
0"
#115000
b10 !
b10 $
1"
#120000
0"
#125000
b11 !
b11 $
1"
#130000
0"
#135000
b100 !
b100 $
1"
#140000
0"
#145000
b101 !
b101 $
1"
#150000
0"
#155000
b110 !
b110 $
1"
#160000
0"
#165000
b111 !
b111 $
1"
#170000
0"
#175000
b1000 !
b1000 $
1"
#180000
0"
#185000
b1001 !
b1001 $
1"
#190000
0"
#195000
b1010 !
b1010 $
1"
