previous projects/ALU, Counter, State Machine/Systolic Array/block.v


module block (
    input clk,
    input wire rst,
    input [15:0] west_input, //inputs from the west
    input [15:0] north_input, // inputs from the north
    
    output reg [15:0] out_south, out_east, 
    output reg [31:0] out  
);
    reg [31:0] product; // temp var to hold product


   always @(posedge clk or posedge rst) begin
    if (rst) begin   // reset
        out <= 32'b0;
        product <= 32'b0;
        out_south <= 16'b0;
        out_east <= 16'b0;
    end
    else begin 
        out <= out + (west_input * north_input);
        out_south <= north_input;
        out_east <=  west_input;
    end  
   end 
endmodule

systolic_array/systolic_array.v

`include "block.v"
module systolic_array (
    input wire clk,
    input wire rst,

    input wire [4:0][15:0] west_0,
    input wire [4:0][15:0] west_1,
    input wire [4:0][15:0] west_2,

    input wire [4:0][15:0] north_0,
    input wire [4:0][15:0] north_1,
    input wire [4:0][15:0] north_2,

    output wire [8:0][31:0] out,
    output reg done 
);
    wire [15:0] out_south[8:0], out_east[8:0];
    reg [2:0] counter;
    reg [15:0] west_in[2:0], north_in[2:0];


    genvar i;
    generate
        for (i = 0; i < 3; i = i + 1) begin : gen_blocks
            block b0 (clk, rst, west_in[i], north_in[i], out_south[i*3], out_east[i*3], out[i*3]);
            block b1 (clk, rst, out_east[i*3], out_south[i*3], out_south[i*3+1], out_east[i*3+1], out[i*3+1]);
            block b2 (clk, rst, out_east[i*3+1], out_south[i*3+1], out_south[i*3+2], out_east[i*3+2], out[i*3+2]);
        end
    endgenerate

    always @(posedge clk or posedge rst) begin
        if (rst) begin 
            counter <= 0;
            done <= 0;
            west_in[0] <= 0; west_in[1] <= 0; west_in[2] <= 0;
            north_in[0] <= 0; north_in[1] <= 0; north_in[2] <= 0;
        end 
        else if (counter < 5) begin 
            counter <= counter + 1 ;

            west_in[0] <= west_0[counter];
            west_in[1] <= west_1[counter];
            west_in[2] <= west_2[counter];
            north_in[0] <= north_0[counter];
            north_in[1] <= north_1[counter];
            north_in[2] <= north_2[counter];
            
            $display("Counter incremented: %0d", counter);
            
            
            $display("Block 00: west_in=%0d, north_in=%0d, out=%0d, out_south=%0d, out_east=%0d", 
                     west_in[0], north_in[0], out[0], out_south[0], out_east[0]);
            $display("Block 10: west_in=%0d, north_in=%0d, out=%0d, out_south=%0d, out_east=%0d", 
                     west_in[1], out_south[0], out[3], out_south[3], out_east[3]);
            $display("Block 22: west_in=%0d, north_in=%0d, out=%0d, out_south=%0d, out_east=%0d", 
                     out_east[7], out_south[7], out[8], out_south[8], out_east[8]);
        end
        else if (counter == 5) begin
            counter <= counter + 1;
        end
        else begin
            done <= 1;
        end
    end

endmodule

systolic_array/systolic_array_tb.v
`timescale 1ns / 1ps

module systolic_array_tb();
    
    reg clk;
    reg rst;
    reg [4:0][15:0] west_0;
    reg [4:0][15:0] west_1;
    reg [4:0][15:0] west_2;
    reg [4:0][15:0] north_0;
    reg [4:0][15:0] north_1;
    reg [4:0][15:0] north_2;
    wire [8:0][31:0] out;
    wire done;

systolic_array uut(

    .clk(clk),
    .rst(rst),

    .west_0(west_0),
    .west_1(west_1),
    .west_2(west_2),

    .north_0(north_0),
    .north_1(north_1),
    .north_2(north_2),

    .out(out),
    .done(done)
);

// Clock generation
initial begin
    clk = 0;
    forever #5 clk = ~clk; // Generate a 100MHz clock
end

initial begin 
    $display("Simulation started");
    rst = 1;  // Start with reset high
    #10 rst = 0;  // De-assert reset after 10 time units
    west_0 = {16'd0, 16'd0, 16'd4, 16'd3, 16'd1};
    west_1 = {16'd0, 16'd9, 16'd8, 16'd5, 16'd0};
    west_2 = {16'd5, 16'd4, 16'd7, 16'd0, 16'd0};

    north_0 = {16'd0, 16'd0, 16'd4, 16'd3, 16'd7};
    north_1 = {16'd0, 16'd7, 16'd6, 16'd8, 16'd0};
    north_2 = {16'd3, 16'd7, 16'd2, 16'd0, 16'd0};
    #1000;
    wait(done);

    $display("Systolic Array Output:");
    for (integer i = 0; i < 9; i = i + 1) begin
        $display("out[%0d] = %0d", i, out[i]);
    end

    #100 $finish;  // End simulation

end 

// VCD file generation
initial begin
    $dumpfile("systolic_sim.vcd");
    $dumpvars(0, systolic_array_tb);
end

endmodule

systolic_sim.vcd
$date
	Mon Sep 30 16:13:04 2024
$end
$version
	Icarus Verilog
$end
$timescale
	1ps
$end
$scope module systolic_array_tb $end
$var wire 288 ! out [287:0] $end
$var wire 1 " done $end
$var reg 1 # clk $end
$var reg 80 $ north_0 [79:0] $end
$var reg 80 % north_1 [79:0] $end
$var reg 80 & north_2 [79:0] $end
$var reg 1 ' rst $end
$var reg 80 ( west_0 [79:0] $end
$var reg 80 ) west_1 [79:0] $end
$var reg 80 * west_2 [79:0] $end
$scope module uut $end
$var wire 1 # clk $end
$var wire 80 + north_0 [79:0] $end
$var wire 80 , north_1 [79:0] $end
$var wire 80 - north_2 [79:0] $end
$var wire 1 ' rst $end
$var wire 80 . west_0 [79:0] $end
$var wire 80 / west_1 [79:0] $end
$var wire 80 0 west_2 [79:0] $end
$var wire 288 1 out [287:0] $end
$var reg 3 2 counter [2:0] $end
$var reg 1 " done $end
$scope begin gen_blocks[0] $end
$var parameter 2 3 i $end
$scope module b0 $end
$var wire 1 # clk $end
$var wire 16 4 north_input [15:0] $end
$var wire 1 ' rst $end
$var wire 16 5 west_input [15:0] $end
$var reg 32 6 out [31:0] $end
$var reg 16 7 out_east [15:0] $end
$var reg 16 8 out_south [15:0] $end
$var reg 32 9 product [31:0] $end
$upscope $end
$scope module b1 $end
$var wire 1 # clk $end
$var wire 16 : north_input [15:0] $end
$var wire 1 ' rst $end
$var wire 16 ; west_input [15:0] $end
$var reg 32 < out [31:0] $end
$var reg 16 = out_east [15:0] $end
$var reg 16 > out_south [15:0] $end
$var reg 32 ? product [31:0] $end
$upscope $end
$scope module b2 $end
$var wire 1 # clk $end
$var wire 16 @ north_input [15:0] $end
$var wire 1 ' rst $end
$var wire 16 A west_input [15:0] $end
$var reg 32 B out [31:0] $end
$var reg 16 C out_east [15:0] $end
$var reg 16 D out_south [15:0] $end
$var reg 32 E product [31:0] $end
$upscope $end
$upscope $end
$scope begin gen_blocks[1] $end
$var parameter 2 F i $end
$scope module b0 $end
$var wire 1 # clk $end
$var wire 16 G north_input [15:0] $end
$var wire 1 ' rst $end
$var wire 16 H west_input [15:0] $end
$var reg 32 I out [31:0] $end
$var reg 16 J out_east [15:0] $end
$var reg 16 K out_south [15:0] $end
$var reg 32 L product [31:0] $end
$upscope $end
$scope module b1 $end
$var wire 1 # clk $end
$var wire 16 M north_input [15:0] $end
$var wire 1 ' rst $end
$var wire 16 N west_input [15:0] $end
$var reg 32 O out [31:0] $end
$var reg 16 P out_east [15:0] $end
$var reg 16 Q out_south [15:0] $end
$var reg 32 R product [31:0] $end
$upscope $end
$scope module b2 $end
$var wire 1 # clk $end
$var wire 16 S north_input [15:0] $end
$var wire 1 ' rst $end
$var wire 16 T west_input [15:0] $end
$var reg 32 U out [31:0] $end
$var reg 16 V out_east [15:0] $end
$var reg 16 W out_south [15:0] $end
$var reg 32 X product [31:0] $end
$upscope $end
$upscope $end
$scope begin gen_blocks[2] $end
$var parameter 3 Y i $end
$scope module b0 $end
$var wire 1 # clk $end
$var wire 16 Z north_input [15:0] $end
$var wire 1 ' rst $end
$var wire 16 [ west_input [15:0] $end
$var reg 32 \ out [31:0] $end
$var reg 16 ] out_east [15:0] $end
$var reg 16 ^ out_south [15:0] $end
$var reg 32 _ product [31:0] $end
$upscope $end
$scope module b1 $end
$var wire 1 # clk $end
$var wire 16 ` north_input [15:0] $end
$var wire 1 ' rst $end
$var wire 16 a west_input [15:0] $end
$var reg 32 b out [31:0] $end
$var reg 16 c out_east [15:0] $end
$var reg 16 d out_south [15:0] $end
$var reg 32 e product [31:0] $end
$upscope $end
$scope module b2 $end
$var wire 1 # clk $end
$var wire 16 f north_input [15:0] $end
$var wire 1 ' rst $end
$var wire 16 g west_input [15:0] $end
$var reg 32 h out [31:0] $end
$var reg 16 i out_east [15:0] $end
$var reg 16 j out_south [15:0] $end
$var reg 32 k product [31:0] $end
$upscope $end
$upscope $end
$upscope $end
$scope begin $ivl_for_loop0 $end
$var integer 32 l i [31:0] $end
$upscope $end
$upscope $end
$enddefinitions $end
$comment Show the parameter values. $end
$dumpall
b10 Y
b1 F
b0 3
$end
#0
$dumpvars
bx l
b0 k
b0 j
b0 i
b0 h
b0 g
b0 f
b0 e
b0 d
b0 c
b0 b
b0 a
b0 `
b0 _
b0 ^
b0 ]
b0 \
b0 [
b0 Z
b0 X
b0 W
b0 V
b0 U
b0 T
b0 S
b0 R
b0 Q
b0 P
b0 O
b0 N
b0 M
b0 L
b0 K
b0 J
b0 I
b0 H
b0 G
b0 E
b0 D
b0 C
b0 B
b0 A
b0 @
b0 ?
b0 >
b0 =
b0 <
b0 ;
b0 :
b0 9
b0 8
b0 7
b0 6
b0 5
b0 4
b0 2
b0 1
bx 0
bx /
bx .
bx -
bx ,
bx +
bx *
bx )
bx (
1'
bx &
bx %
bx $
0#
0"
b0 !
$end
#5000
1#
#10000
0#
b110000000000000111000000000000001000000000000000000000000000000000 &
b110000000000000111000000000000001000000000000000000000000000000000 -
b111000000000000011000000000000010000000000000000000 %
b111000000000000011000000000000010000000000000000000 ,
b10000000000000000110000000000000111 $
b10000000000000000110000000000000111 +
b1010000000000000100000000000000011100000000000000000000000000000000 *
b1010000000000000100000000000000011100000000000000000000000000000000 0
b1001000000000000100000000000000001010000000000000000 )
b1001000000000000100000000000000001010000000000000000 /
b10000000000000000110000000000000001 (
b10000000000000000110000000000000001 .
0'
#15000
b111 4
b1 5
b1 2
1#
#20000
0#
#25000
b1000 G
b11 4
b101 H
b11 5
b10 2
b1 7
b1 ;
b111 8
b111 :
b111 !
b111 1
b111 6
b111 9
1#
#30000
0#
#35000
b11 7
b11 ;
b11 8
b11 :
b10000 6
b1 =
b1 A
b111 >
b111 @
b111 <
b101 J
b101 N
b1000 K
b1000 M
b101000000000000000000000000000000000000000000000000000000000000000011100000000000000000000000000010000 !
b101000000000000000000000000000000000000000000000000000000000000000011100000000000000000000000000010000 1
b101000 I
b10 Z
b110 G
b100 4
b111 [
b1000 H
b100 5
b11 2
b1001 9
b111 ?
b101000 L
1#
#40000
0#
#45000
b111 Z
b111 G
b0 4
b100 [
b1001 H
b0 5
b100 2
b111 ]
b111 a
b10 ^
b10 `
b1110 \
b101 P
b101 T
b1000 Q
b1000 S
b101000 O
b1000 J
b1000 N
b110 K
b110 M
b1011000 I
b1 C
b111 D
b111 B
b11 =
b11 A
b11 >
b11 @
b10000 <
b100 7
b100 ;
b100 8
b100 :
b1110000000000000000000000000000000000000000000000000000000000010100000000000000000000000000001011000000000000000000000000000000001110000000000000000000000000001000000000000000000000000000000100000 !
b1110000000000000000000000000000000000000000000000000000000000010100000000000000000000000000001011000000000000000000000000000000001110000000000000000000000000001000000000000000000000000000000100000 1
b100000 6
b1110 _
b101000 R
b110000 L
b111 E
b1001 ?
b10000 9
1#
#50000
0#
#55000
b0 7
b0 ;
b0 8
b0 :
b100 =
b100 A
b100 >
b100 @
b100000 <
b11 C
b11 D
b10000 B
b1001 J
b1001 N
b111 K
b111 M
b10010111 I
b1000 P
b1000 T
b110 Q
b110 S
b1011000 O
b101 V
b1000 W
b101000 U
b100 ]
b100 a
b111 ^
b111 `
b101010 \
b111 c
b111 g
b10 d
b10 f
b111000000000000000000000000000101010000000000000000000000000001010000000000000000000000000000101100000000000000000000000000010010111000000000000000000000000000100000000000000000000000000000010000000000000000000000000000000100000 !
b111000000000000000000000000000101010000000000000000000000000001010000000000000000000000000000101100000000000000000000000000010010111000000000000000000000000000100000000000000000000000000000010000000000000000000000000000000100000 1
b1110 b
b11 Z
b0 G
b101 [
b0 H
b101 2
b0 9
b10000 ?
b1001 E
b111111 L
b110000 R
b101000 X
b11100 _
b1110 e
1#
#60000
0#
#65000
b110 2
b111 i
b10 j
b1110 h
b100 c
b100 g
b111 d
b111 f
b101010 b
b101 ]
b101 a
b11 ^
b11 `
b111001 \
b1000 V
b110 W
b1011000 U
b1001 P
b1001 T
b111 Q
b111 S
b10010111 O
b0 J
b0 N
b0 K
b0 M
b100 C
b100 D
b11100000000000000000000000000010101000000000000000000000000000111001000000000000000000000000010110000000000000000000000000001001011100000000000000000000000010010111000000000000000000000000001000000000000000000000000000000010000000000000000000000000000000100000 !
b11100000000000000000000000000010101000000000000000000000000000111001000000000000000000000000010110000000000000000000000000001001011100000000000000000000000010010111000000000000000000000000001000000000000000000000000000000010000000000000000000000000000000100000 1
b100000 B
b0 =
b0 A
b0 >
b0 @
b1110 k
b11100 e
b1111 _
b110000 X
b111111 R
b0 L
b10000 E
b0 ?
1#
#70000
0#
#75000
b0 C
b0 D
b0 P
b0 T
b0 Q
b0 S
b1001 V
b111 W
b10010111 U
b1001000 \
b101 c
b101 g
b11 d
b11 f
b111001 b
b100 i
b111 j
b1010100000000000000000000000000011100100000000000000000000000001001000000000000000000000000000100101110000000000000000000000001001011100000000000000000000000010010111000000000000000000000000001000000000000000000000000000000010000000000000000000000000000000100000 !
b1010100000000000000000000000000011100100000000000000000000000001001000000000000000000000000000100101110000000000000000000000001001011100000000000000000000000010010111000000000000000000000000001000000000000000000000000000000010000000000000000000000000000000100000 1
b101010 h
1"
b0 E
b0 R
b111111 X
b1111 e
b11100 k
1#
#80000
0#
#85000
b101 i
b11 j
b111001 h
b1001000 b
b1110010000000000000000000000000100100000000000000000000000000001010111000000000000000000000000100101110000000000000000000000001001011100000000000000000000000010010111000000000000000000000000001000000000000000000000000000000010000000000000000000000000000000100000 !
b1110010000000000000000000000000100100000000000000000000000000001010111000000000000000000000000100101110000000000000000000000001001011100000000000000000000000010010111000000000000000000000000001000000000000000000000000000000010000000000000000000000000000000100000 1
b1010111 \
b0 V
b0 W
b1111 k
b0 X
1#
#90000
0#
#95000
b1100110 \
b1010111 b
b10010000000000000000000000000000101011100000000000000000000000001100110000000000000000000000000100101110000000000000000000000001001011100000000000000000000000010010111000000000000000000000000001000000000000000000000000000000010000000000000000000000000000000100000 !
b10010000000000000000000000000000101011100000000000000000000000001100110000000000000000000000000100101110000000000000000000000001001011100000000000000000000000010010111000000000000000000000000001000000000000000000000000000000010000000000000000000000000000000100000 1
b1001000 h
1#
#100000
0#
#105000
b1010111 h
b1100110 b
b10101110000000000000000000000000110011000000000000000000000000001110101000000000000000000000000100101110000000000000000000000001001011100000000000000000000000010010111000000000000000000000000001000000000000000000000000000000010000000000000000000000000000000100000 !
b10101110000000000000000000000000110011000000000000000000000000001110101000000000000000000000000100101110000000000000000000000001001011100000000000000000000000010010111000000000000000000000000001000000000000000000000000000000010000000000000000000000000000000100000 1
b1110101 \
1#
#110000
0#
#115000
b10000100 \
b1110101 b
b11001100000000000000000000000000111010100000000000000000000000010000100000000000000000000000000100101110000000000000000000000001001011100000000000000000000000010010111000000000000000000000000001000000000000000000000000000000010000000000000000000000000000000100000 !
b11001100000000000000000000000000111010100000000000000000000000010000100000000000000000000000000100101110000000000000000000000001001011100000000000000000000000010010111000000000000000000000000001000000000000000000000000000000010000000000000000000000000000000100000 1
b1100110 h
1#
#120000
0#
#125000
b1110101 h
b10000100 b
b11101010000000000000000000000001000010000000000000000000000000010010011000000000000000000000000100101110000000000000000000000001001011100000000000000000000000010010111000000000000000000000000001000000000000000000000000000000010000000000000000000000000000000100000 !
b11101010000000000000000000000001000010000000000000000000000000010010011000000000000000000000000100101110000000000000000000000001001011100000000000000000000000010010111000000000000000000000000001000000000000000000000000000000010000000000000000000000000000000100000 1
b10010011 \
1#
#130000
0#
#135000
b10100010 \
b10010011 b
b100001000000000000000000000000001001001100000000000000000000000010100010000000000000000000000000100101110000000000000000000000001001011100000000000000000000000010010111000000000000000000000000001000000000000000000000000000000010000000000000000000000000000000100000 !
b100001000000000000000000000000001001001100000000000000000000000010100010000000000000000000000000100101110000000000000000000000001001011100000000000000000000000010010111000000000000000000000000001000000000000000000000000000000010000000000000000000000000000000100000 1
b10000100 h
1#
#140000
0#
#145000
b10010011 h
b10100010 b
b100100110000000000000000000000001010001000000000000000000000000010110001000000000000000000000000100101110000000000000000000000001001011100000000000000000000000010010111000000000000000000000000001000000000000000000000000000000010000000000000000000000000000000100000 !
b100100110000000000000000000000001010001000000000000000000000000010110001000000000000000000000000100101110000000000000000000000001001011100000000000000000000000010010111000000000000000000000000001000000000000000000000000000000010000000000000000000000000000000100000 1
b10110001 \
1#
#150000
0#
#155000
b11000000 \
b10110001 b
b101000100000000000000000000000001011000100000000000000000000000011000000000000000000000000000000100101110000000000000000000000001001011100000000000000000000000010010111000000000000000000000000001000000000000000000000000000000010000000000000000000000000000000100000 !
b101000100000000000000000000000001011000100000000000000000000000011000000000000000000000000000000100101110000000000000000000000001001011100000000000000000000000010010111000000000000000000000000001000000000000000000000000000000010000000000000000000000000000000100000 1
b10100010 h
1#
#160000
0#
#165000
b10110001 h
b11000000 b
b101100010000000000000000000000001100000000000000000000000000000011001111000000000000000000000000100101110000000000000000000000001001011100000000000000000000000010010111000000000000000000000000001000000000000000000000000000000010000000000000000000000000000000100000 !
b101100010000000000000000000000001100000000000000000000000000000011001111000000000000000000000000100101110000000000000000000000001001011100000000000000000000000010010111000000000000000000000000001000000000000000000000000000000010000000000000000000000000000000100000 1
b11001111 \
1#
#170000
0#
#175000
b11011110 \
b11001111 b
b110000000000000000000000000000001100111100000000000000000000000011011110000000000000000000000000100101110000000000000000000000001001011100000000000000000000000010010111000000000000000000000000001000000000000000000000000000000010000000000000000000000000000000100000 !
b110000000000000000000000000000001100111100000000000000000000000011011110000000000000000000000000100101110000000000000000000000001001011100000000000000000000000010010111000000000000000000000000001000000000000000000000000000000010000000000000000000000000000000100000 1
b11000000 h
1#
#180000
0#
#185000
b11001111 h
b11011110 b
b110011110000000000000000000000001101111000000000000000000000000011101101000000000000000000000000100101110000000000000000000000001001011100000000000000000000000010010111000000000000000000000000001000000000000000000000000000000010000000000000000000000000000000100000 !
b110011110000000000000000000000001101111000000000000000000000000011101101000000000000000000000000100101110000000000000000000000001001011100000000000000000000000010010111000000000000000000000000001000000000000000000000000000000010000000000000000000000000000000100000 1
b11101101 \
1#
#190000
0#
#195000
b11111100 \
b11101101 b
b110111100000000000000000000000001110110100000000000000000000000011111100000000000000000000000000100101110000000000000000000000001001011100000000000000000000000010010111000000000000000000000000001000000000000000000000000000000010000000000000000000000000000000100000 !
b110111100000000000000000000000001110110100000000000000000000000011111100000000000000000000000000100101110000000000000000000000001001011100000000000000000000000010010111000000000000000000000000001000000000000000000000000000000010000000000000000000000000000000100000 1
b11011110 h
1#
#200000
0#
#205000
b11101101 h
b11111100 b
b111011010000000000000000000000001111110000000000000000000000000100001011000000000000000000000000100101110000000000000000000000001001011100000000000000000000000010010111000000000000000000000000001000000000000000000000000000000010000000000000000000000000000000100000 !
b111011010000000000000000000000001111110000000000000000000000000100001011000000000000000000000000100101110000000000000000000000001001011100000000000000000000000010010111000000000000000000000000001000000000000000000000000000000010000000000000000000000000000000100000 1
b100001011 \
1#
#210000
0#
#215000
b100011010 \
b100001011 b
b111111000000000000000000000000010000101100000000000000000000000100011010000000000000000000000000100101110000000000000000000000001001011100000000000000000000000010010111000000000000000000000000001000000000000000000000000000000010000000000000000000000000000000100000 !
b111111000000000000000000000000010000101100000000000000000000000100011010000000000000000000000000100101110000000000000000000000001001011100000000000000000000000010010111000000000000000000000000001000000000000000000000000000000010000000000000000000000000000000100000 1
b11111100 h
1#
#220000
0#
#225000
b100001011 h
b100011010 b
b1000010110000000000000000000000010001101000000000000000000000000100101001000000000000000000000000100101110000000000000000000000001001011100000000000000000000000010010111000000000000000000000000001000000000000000000000000000000010000000000000000000000000000000100000 !
b1000010110000000000000000000000010001101000000000000000000000000100101001000000000000000000000000100101110000000000000000000000001001011100000000000000000000000010010111000000000000000000000000001000000000000000000000000000000010000000000000000000000000000000100000 1
b100101001 \
1#
#230000
0#
#235000
b100111000 \
b100101001 b
b1000110100000000000000000000000010010100100000000000000000000000100111000000000000000000000000000100101110000000000000000000000001001011100000000000000000000000010010111000000000000000000000000001000000000000000000000000000000010000000000000000000000000000000100000 !
b1000110100000000000000000000000010010100100000000000000000000000100111000000000000000000000000000100101110000000000000000000000001001011100000000000000000000000010010111000000000000000000000000001000000000000000000000000000000010000000000000000000000000000000100000 1
b100011010 h
1#
#240000
0#
#245000
b100101001 h
b100111000 b
b1001010010000000000000000000000010011100000000000000000000000000101000111000000000000000000000000100101110000000000000000000000001001011100000000000000000000000010010111000000000000000000000000001000000000000000000000000000000010000000000000000000000000000000100000 !
b1001010010000000000000000000000010011100000000000000000000000000101000111000000000000000000000000100101110000000000000000000000001001011100000000000000000000000010010111000000000000000000000000001000000000000000000000000000000010000000000000000000000000000000100000 1
b101000111 \
1#
#250000
0#
#255000
b101010110 \
b101000111 b
b1001110000000000000000000000000010100011100000000000000000000000101010110000000000000000000000000100101110000000000000000000000001001011100000000000000000000000010010111000000000000000000000000001000000000000000000000000000000010000000000000000000000000000000100000 !
b1001110000000000000000000000000010100011100000000000000000000000101010110000000000000000000000000100101110000000000000000000000001001011100000000000000000000000010010111000000000000000000000000001000000000000000000000000000000010000000000000000000000000000000100000 1
b100111000 h
1#
#260000
0#
#265000
b101000111 h
b101010110 b
b1010001110000000000000000000000010101011000000000000000000000000101100101000000000000000000000000100101110000000000000000000000001001011100000000000000000000000010010111000000000000000000000000001000000000000000000000000000000010000000000000000000000000000000100000 !
b1010001110000000000000000000000010101011000000000000000000000000101100101000000000000000000000000100101110000000000000000000000001001011100000000000000000000000010010111000000000000000000000000001000000000000000000000000000000010000000000000000000000000000000100000 1
b101100101 \
1#
#270000
0#
#275000
b101110100 \
b101100101 b
b1010101100000000000000000000000010110010100000000000000000000000101110100000000000000000000000000100101110000000000000000000000001001011100000000000000000000000010010111000000000000000000000000001000000000000000000000000000000010000000000000000000000000000000100000 !
b1010101100000000000000000000000010110010100000000000000000000000101110100000000000000000000000000100101110000000000000000000000001001011100000000000000000000000010010111000000000000000000000000001000000000000000000000000000000010000000000000000000000000000000100000 1
b101010110 h
1#
#280000
0#
#285000
b101100101 h
b101110100 b
b1011001010000000000000000000000010111010000000000000000000000000110000011000000000000000000000000100101110000000000000000000000001001011100000000000000000000000010010111000000000000000000000000001000000000000000000000000000000010000000000000000000000000000000100000 !
b1011001010000000000000000000000010111010000000000000000000000000110000011000000000000000000000000100101110000000000000000000000001001011100000000000000000000000010010111000000000000000000000000001000000000000000000000000000000010000000000000000000000000000000100000 1
b110000011 \
1#
#290000
0#
#295000
b110010010 \
b110000011 b
b1011101000000000000000000000000011000001100000000000000000000000110010010000000000000000000000000100101110000000000000000000000001001011100000000000000000000000010010111000000000000000000000000001000000000000000000000000000000010000000000000000000000000000000100000 !
b1011101000000000000000000000000011000001100000000000000000000000110010010000000000000000000000000100101110000000000000000000000001001011100000000000000000000000010010111000000000000000000000000001000000000000000000000000000000010000000000000000000000000000000100000 1
b101110100 h
1#
#300000
0#
#305000
b110000011 h
b110010010 b
b1100000110000000000000000000000011001001000000000000000000000000110100001000000000000000000000000100101110000000000000000000000001001011100000000000000000000000010010111000000000000000000000000001000000000000000000000000000000010000000000000000000000000000000100000 !
b1100000110000000000000000000000011001001000000000000000000000000110100001000000000000000000000000100101110000000000000000000000001001011100000000000000000000000010010111000000000000000000000000001000000000000000000000000000000010000000000000000000000000000000100000 1
b110100001 \
1#
#310000
0#
#315000
b110110000 \
b110100001 b
b1100100100000000000000000000000011010000100000000000000000000000110110000000000000000000000000000100101110000000000000000000000001001011100000000000000000000000010010111000000000000000000000000001000000000000000000000000000000010000000000000000000000000000000100000 !
b1100100100000000000000000000000011010000100000000000000000000000110110000000000000000000000000000100101110000000000000000000000001001011100000000000000000000000010010111000000000000000000000000001000000000000000000000000000000010000000000000000000000000000000100000 1
b110010010 h
1#
#320000
0#
#325000
b110100001 h
b110110000 b
b1101000010000000000000000000000011011000000000000000000000000000110111111000000000000000000000000100101110000000000000000000000001001011100000000000000000000000010010111000000000000000000000000001000000000000000000000000000000010000000000000000000000000000000100000 !
b1101000010000000000000000000000011011000000000000000000000000000110111111000000000000000000000000100101110000000000000000000000001001011100000000000000000000000010010111000000000000000000000000001000000000000000000000000000000010000000000000000000000000000000100000 1
b110111111 \
1#
#330000
0#
#335000
b111001110 \
b110111111 b
b1101100000000000000000000000000011011111100000000000000000000000111001110000000000000000000000000100101110000000000000000000000001001011100000000000000000000000010010111000000000000000000000000001000000000000000000000000000000010000000000000000000000000000000100000 !
b1101100000000000000000000000000011011111100000000000000000000000111001110000000000000000000000000100101110000000000000000000000001001011100000000000000000000000010010111000000000000000000000000001000000000000000000000000000000010000000000000000000000000000000100000 1
b110110000 h
1#
#340000
0#
#345000
b110111111 h
b111001110 b
b1101111110000000000000000000000011100111000000000000000000000000111011101000000000000000000000000100101110000000000000000000000001001011100000000000000000000000010010111000000000000000000000000001000000000000000000000000000000010000000000000000000000000000000100000 !
b1101111110000000000000000000000011100111000000000000000000000000111011101000000000000000000000000100101110000000000000000000000001001011100000000000000000000000010010111000000000000000000000000001000000000000000000000000000000010000000000000000000000000000000100000 1
b111011101 \
1#
#350000
0#
#355000
b111101100 \
b111011101 b
b1110011100000000000000000000000011101110100000000000000000000000111101100000000000000000000000000100101110000000000000000000000001001011100000000000000000000000010010111000000000000000000000000001000000000000000000000000000000010000000000000000000000000000000100000 !
b1110011100000000000000000000000011101110100000000000000000000000111101100000000000000000000000000100101110000000000000000000000001001011100000000000000000000000010010111000000000000000000000000001000000000000000000000000000000010000000000000000000000000000000100000 1
b111001110 h
1#
#360000
0#
#365000
b111011101 h
b111101100 b
b1110111010000000000000000000000011110110000000000000000000000000111111011000000000000000000000000100101110000000000000000000000001001011100000000000000000000000010010111000000000000000000000000001000000000000000000000000000000010000000000000000000000000000000100000 !
b1110111010000000000000000000000011110110000000000000000000000000111111011000000000000000000000000100101110000000000000000000000001001011100000000000000000000000010010111000000000000000000000000001000000000000000000000000000000010000000000000000000000000000000100000 1
b111111011 \
1#
#370000
0#
#375000
b1000001010 \
b111111011 b
b1111011000000000000000000000000011111101100000000000000000000001000001010000000000000000000000000100101110000000000000000000000001001011100000000000000000000000010010111000000000000000000000000001000000000000000000000000000000010000000000000000000000000000000100000 !
b1111011000000000000000000000000011111101100000000000000000000001000001010000000000000000000000000100101110000000000000000000000001001011100000000000000000000000010010111000000000000000000000000001000000000000000000000000000000010000000000000000000000000000000100000 1
b111101100 h
1#
#380000
0#
#385000
b111111011 h
b1000001010 b
b1111110110000000000000000000000100000101000000000000000000000001000011001000000000000000000000000100101110000000000000000000000001001011100000000000000000000000010010111000000000000000000000000001000000000000000000000000000000010000000000000000000000000000000100000 !
b1111110110000000000000000000000100000101000000000000000000000001000011001000000000000000000000000100101110000000000000000000000001001011100000000000000000000000010010111000000000000000000000000001000000000000000000000000000000010000000000000000000000000000000100000 1
b1000011001 \
1#
#390000
0#
#395000
b1000101000 \
b1000011001 b
b10000010100000000000000000000000100001100100000000000000000000001000101000000000000000000000000000100101110000000000000000000000001001011100000000000000000000000010010111000000000000000000000000001000000000000000000000000000000010000000000000000000000000000000100000 !
b10000010100000000000000000000000100001100100000000000000000000001000101000000000000000000000000000100101110000000000000000000000001001011100000000000000000000000010010111000000000000000000000000001000000000000000000000000000000010000000000000000000000000000000100000 1
b1000001010 h
1#
#400000
0#
#405000
b1000011001 h
b1000101000 b
b10000110010000000000000000000000100010100000000000000000000000001000110111000000000000000000000000100101110000000000000000000000001001011100000000000000000000000010010111000000000000000000000000001000000000000000000000000000000010000000000000000000000000000000100000 !
b10000110010000000000000000000000100010100000000000000000000000001000110111000000000000000000000000100101110000000000000000000000001001011100000000000000000000000010010111000000000000000000000000001000000000000000000000000000000010000000000000000000000000000000100000 1
b1000110111 \
1#
#410000
0#
#415000
b1001000110 \
b1000110111 b
b10001010000000000000000000000000100011011100000000000000000000001001000110000000000000000000000000100101110000000000000000000000001001011100000000000000000000000010010111000000000000000000000000001000000000000000000000000000000010000000000000000000000000000000100000 !
b10001010000000000000000000000000100011011100000000000000000000001001000110000000000000000000000000100101110000000000000000000000001001011100000000000000000000000010010111000000000000000000000000001000000000000000000000000000000010000000000000000000000000000000100000 1
b1000101000 h
1#
#420000
0#
#425000
b1000110111 h
b1001000110 b
b10001101110000000000000000000000100100011000000000000000000000001001010101000000000000000000000000100101110000000000000000000000001001011100000000000000000000000010010111000000000000000000000000001000000000000000000000000000000010000000000000000000000000000000100000 !
b10001101110000000000000000000000100100011000000000000000000000001001010101000000000000000000000000100101110000000000000000000000001001011100000000000000000000000010010111000000000000000000000000001000000000000000000000000000000010000000000000000000000000000000100000 1
b1001010101 \
1#
#430000
0#
#435000
b1001100100 \
b1001010101 b
b10010001100000000000000000000000100101010100000000000000000000001001100100000000000000000000000000100101110000000000000000000000001001011100000000000000000000000010010111000000000000000000000000001000000000000000000000000000000010000000000000000000000000000000100000 !
b10010001100000000000000000000000100101010100000000000000000000001001100100000000000000000000000000100101110000000000000000000000001001011100000000000000000000000010010111000000000000000000000000001000000000000000000000000000000010000000000000000000000000000000100000 1
b1001000110 h
1#
#440000
0#
#445000
b1001010101 h
b1001100100 b
b10010101010000000000000000000000100110010000000000000000000000001001110011000000000000000000000000100101110000000000000000000000001001011100000000000000000000000010010111000000000000000000000000001000000000000000000000000000000010000000000000000000000000000000100000 !
b10010101010000000000000000000000100110010000000000000000000000001001110011000000000000000000000000100101110000000000000000000000001001011100000000000000000000000010010111000000000000000000000000001000000000000000000000000000000010000000000000000000000000000000100000 1
b1001110011 \
1#
#450000
0#
