previous projects/ALU, Counter, State Machine/Systolic Array/block.v


module block (
    input clk,
    input wire rst,
    input [15:0] west_input, //inputs from the west
    input [15:0] north_input, // inputs from the north
    
    output reg [15:0] out_south, out_east, 
    output reg [31:0] out  
);
    reg [31:0] product; // temp var to hold product


   always @(posedge clk or posedge rst) begin
    if (rst) begin   // reset
        out <= 32'b0;
        product <= 32'b0;
        out_south <= 16'b0;
        out_east <= 16'b0;
    end
    else begin 
        out <= out + (west_input * north_input);
        out_south <= north_input;
        out_east <=  west_input;
    end  
   end 
endmodule

previous projects/ALU, Counter, State Machine/Systolic Array/systolic_array.v

`include "block.v"
module systolic_array (
    input wire clk,
    input wire rst,

    input wire [4:0][15:0] west_0,
    input wire [4:0][15:0] west_1,
    input wire [4:0][15:0] west_2,

    input wire [4:0][15:0] north_0,
    input wire [4:0][15:0] north_1,
    input wire [4:0][15:0] north_2,

    output wire [8:0][31:0] out,
    output reg done 
);
    wire [15:0] out_south[8:0], out_east[8:0];
    reg [3:0] counter;
    reg [15:0] west_in[2:0], north_in[2:0];


    // First row
    block b00 (clk, rst, west_in[0], north_in[0], out_south[0], out_east[0], out[0]);
    block b01 (clk, rst, out_east[0], north_in[1], out_south[1], out_east[1], out[1]);
    block b02 (clk, rst, out_east[1], north_in[2], out_south[2], out_east[2], out[2]);

    // Second row
    block b10 (clk, rst, west_in[1], out_south[0], out_south[3], out_east[3], out[3]);
    block b11 (clk, rst, out_east[3], out_south[1], out_south[4], out_east[4], out[4]);
    block b12 (clk, rst, out_east[4], out_south[2], out_south[5], out_east[5], out[5]);

    // Third row
    block b20 (clk, rst, west_in[2], out_south[3], out_south[6], out_east[6], out[6]);
    block b21 (clk, rst, out_east[6], out_south[4], out_south[7], out_east[7], out[7]);
    block b22 (clk, rst, out_east[7], out_south[5], out_south[8], out_east[8], out[8]);

    always @(posedge clk or posedge rst) begin
        if (rst) begin 
            counter <= 0;
            done <= 0;
            west_in[0] <= 0; west_in[1] <= 0; west_in[2] <= 0;
            north_in[0] <= 0; north_in[1] <= 0; north_in[2] <= 0;
        end 
        else if (counter < 5) begin 

            west_in[0] <= west_0[counter];
            west_in[1] <= west_1[counter];
            west_in[2] <= west_2[counter];

            north_in[0] <= north_0[counter];
            north_in[1] <= north_1[counter];
            north_in[2] <= north_2[counter];

            counter <= counter + 1 ;
        end
        else if (counter == 5) begin
            counter <= counter + 1;
        end
        else begin
            done <= 1;
        end
    end

endmodule

Systolic Array/systolic_array_tb.v
`timescale 1ns / 1ps

module systolic_array_tb();
    
    reg clk;
    reg rst;
    reg [4:0][15:0] west_0;
    reg [4:0][15:0] west_1;
    reg [4:0][15:0] west_2;
    reg [4:0][15:0] north_0;
    reg [4:0][15:0] north_1;
    reg [4:0][15:0] north_2;
    wire [8:0][31:0] out;
    wire done;
        // Add wire declarations for out_south and out_east
    wire [15:0] out_south[8:0];
    wire [15:0] out_east[8:0];

systolic_array uut(

    .clk(clk),
    .rst(rst),

    .west_0(west_0),
    .west_1(west_1),
    .west_2(west_2),

    .north_0(north_0),
    .north_1(north_1),
    .north_2(north_2),

    .out(out),
    .done(done)
);

// Clock generation
initial begin
    clk = 0;
    forever #5 clk = ~clk; // Generate a 100MHz clock
end

initial begin 
    $display("Simulation started");
    rst = 1;  // Start with reset high
    #10 rst = 0;  // De-assert reset after 10 time units
    west_0 = {16'd0, 16'd0, 16'd4, 16'd3, 16'd1};
    west_1 = {16'd0, 16'd9, 16'd8, 16'd5, 16'd0};
    west_2 = {16'd3, 16'd1, 16'd1, 16'd0, 16'd0};

    north_0 = {16'd0, 16'd0, 16'd4, 16'd3, 16'd7};
    north_1 = {16'd0, 16'd1, 16'd6, 16'd8, 16'd0};
    north_2 = {16'd3, 16'd7, 16'd2, 16'd0, 16'd0};
    #80;
    wait(done);

    $display("Systolic Array Output:");
    for (integer i = 0; i < 9; i = i + 1) begin
        $display("out[%0d] = %0d", i, out[i]);
    end

    $finish;  // End simulation

end 

// VCD file generation
initial begin
    $dumpfile("systolic_sim.vcd");
    $dumpvars(0, systolic_array_tb);
end

endmodule

systolic_sim.vcd
$date
	Tue Oct 01 12:04:48 2024
$end
$version
	Icarus Verilog
$end
$timescale
	1ps
$end
$scope module systolic_array_tb $end
$var wire 288 ! out [287:0] $end
$var wire 1 " done $end
$var reg 1 # clk $end
$var reg 80 $ north_0 [79:0] $end
$var reg 80 % north_1 [79:0] $end
$var reg 80 & north_2 [79:0] $end
$var reg 1 ' rst $end
$var reg 80 ( west_0 [79:0] $end
$var reg 80 ) west_1 [79:0] $end
$var reg 80 * west_2 [79:0] $end
$scope module uut $end
$var wire 1 # clk $end
$var wire 80 + north_0 [79:0] $end
$var wire 80 , north_1 [79:0] $end
$var wire 80 - north_2 [79:0] $end
$var wire 1 ' rst $end
$var wire 80 . west_0 [79:0] $end
$var wire 80 / west_1 [79:0] $end
$var wire 80 0 west_2 [79:0] $end
$var wire 288 1 out [287:0] $end
$var reg 4 2 counter [3:0] $end
$var reg 1 " done $end
$scope module b00 $end
$var wire 1 # clk $end
$var wire 16 3 north_input [15:0] $end
$var wire 1 ' rst $end
$var wire 16 4 west_input [15:0] $end
$var reg 32 5 out [31:0] $end
$var reg 16 6 out_east [15:0] $end
$var reg 16 7 out_south [15:0] $end
$var reg 32 8 product [31:0] $end
$upscope $end
$scope module b01 $end
$var wire 1 # clk $end
$var wire 16 9 north_input [15:0] $end
$var wire 1 ' rst $end
$var wire 16 : west_input [15:0] $end
$var reg 32 ; out [31:0] $end
$var reg 16 < out_east [15:0] $end
$var reg 16 = out_south [15:0] $end
$var reg 32 > product [31:0] $end
$upscope $end
$scope module b02 $end
$var wire 1 # clk $end
$var wire 16 ? north_input [15:0] $end
$var wire 1 ' rst $end
$var wire 16 @ west_input [15:0] $end
$var reg 32 A out [31:0] $end
$var reg 16 B out_east [15:0] $end
$var reg 16 C out_south [15:0] $end
$var reg 32 D product [31:0] $end
$upscope $end
$scope module b10 $end
$var wire 1 # clk $end
$var wire 16 E north_input [15:0] $end
$var wire 1 ' rst $end
$var wire 16 F west_input [15:0] $end
$var reg 32 G out [31:0] $end
$var reg 16 H out_east [15:0] $end
$var reg 16 I out_south [15:0] $end
$var reg 32 J product [31:0] $end
$upscope $end
$scope module b11 $end
$var wire 1 # clk $end
$var wire 16 K north_input [15:0] $end
$var wire 1 ' rst $end
$var wire 16 L west_input [15:0] $end
$var reg 32 M out [31:0] $end
$var reg 16 N out_east [15:0] $end
$var reg 16 O out_south [15:0] $end
$var reg 32 P product [31:0] $end
$upscope $end
$scope module b12 $end
$var wire 1 # clk $end
$var wire 16 Q north_input [15:0] $end
$var wire 1 ' rst $end
$var wire 16 R west_input [15:0] $end
$var reg 32 S out [31:0] $end
$var reg 16 T out_east [15:0] $end
$var reg 16 U out_south [15:0] $end
$var reg 32 V product [31:0] $end
$upscope $end
$scope module b20 $end
$var wire 1 # clk $end
$var wire 16 W north_input [15:0] $end
$var wire 1 ' rst $end
$var wire 16 X west_input [15:0] $end
$var reg 32 Y out [31:0] $end
$var reg 16 Z out_east [15:0] $end
$var reg 16 [ out_south [15:0] $end
$var reg 32 \ product [31:0] $end
$upscope $end
$scope module b21 $end
$var wire 1 # clk $end
$var wire 16 ] north_input [15:0] $end
$var wire 1 ' rst $end
$var wire 16 ^ west_input [15:0] $end
$var reg 32 _ out [31:0] $end
$var reg 16 ` out_east [15:0] $end
$var reg 16 a out_south [15:0] $end
$var reg 32 b product [31:0] $end
$upscope $end
$scope module b22 $end
$var wire 1 # clk $end
$var wire 16 c north_input [15:0] $end
$var wire 1 ' rst $end
$var wire 16 d west_input [15:0] $end
$var reg 32 e out [31:0] $end
$var reg 16 f out_east [15:0] $end
$var reg 16 g out_south [15:0] $end
$var reg 32 h product [31:0] $end
$upscope $end
$upscope $end
$scope begin $ivl_for_loop0 $end
$var integer 32 i i [31:0] $end
$upscope $end
$scope begin $ivl_for_loop1 $end
$var integer 32 j i [31:0] $end
$upscope $end
$upscope $end
$scope module systolic_array_tb $end
$scope module uut $end
$var reg 16 k \out_south[0] [15:0] $end
$upscope $end
$upscope $end
$scope module systolic_array_tb $end
$scope module uut $end
$var reg 16 l \out_east[0] [15:0] $end
$upscope $end
$upscope $end
$scope module systolic_array_tb $end
$scope module uut $end
$var reg 16 m \out_south[1] [15:0] $end
$upscope $end
$upscope $end
$scope module systolic_array_tb $end
$scope module uut $end
$var reg 16 n \out_east[1] [15:0] $end
$upscope $end
$upscope $end
$scope module systolic_array_tb $end
$scope module uut $end
$var reg 16 o \out_south[2] [15:0] $end
$upscope $end
$upscope $end
$scope module systolic_array_tb $end
$scope module uut $end
$var reg 16 p \out_east[2] [15:0] $end
$upscope $end
$upscope $end
$scope module systolic_array_tb $end
$scope module uut $end
$var reg 16 q \out_south[3] [15:0] $end
$upscope $end
$upscope $end
$scope module systolic_array_tb $end
$scope module uut $end
$var reg 16 r \out_east[3] [15:0] $end
$upscope $end
$upscope $end
$scope module systolic_array_tb $end
$scope module uut $end
$var reg 16 s \out_south[4] [15:0] $end
$upscope $end
$upscope $end
$scope module systolic_array_tb $end
$scope module uut $end
$var reg 16 t \out_east[4] [15:0] $end
$upscope $end
$upscope $end
$scope module systolic_array_tb $end
$scope module uut $end
$var reg 16 u \out_south[5] [15:0] $end
$upscope $end
$upscope $end
$scope module systolic_array_tb $end
$scope module uut $end
$var reg 16 v \out_east[5] [15:0] $end
$upscope $end
$upscope $end
$scope module systolic_array_tb $end
$scope module uut $end
$var reg 16 w \out_south[6] [15:0] $end
$upscope $end
$upscope $end
$scope module systolic_array_tb $end
$scope module uut $end
$var reg 16 x \out_east[6] [15:0] $end
$upscope $end
$upscope $end
$scope module systolic_array_tb $end
$scope module uut $end
$var reg 16 y \out_south[7] [15:0] $end
$upscope $end
$upscope $end
$scope module systolic_array_tb $end
$scope module uut $end
$var reg 16 z \out_east[7] [15:0] $end
$upscope $end
$upscope $end
$scope module systolic_array_tb $end
$scope module uut $end
$var reg 16 { \out_south[8] [15:0] $end
$upscope $end
$upscope $end
$scope module systolic_array_tb $end
$scope module uut $end
$var reg 16 | \out_east[8] [15:0] $end
$upscope $end
$upscope $end
$enddefinitions $end
$comment Show the parameter values. $end
$dumpall
$end
#0
$dumpvars
b0 |
b0 {
b0 z
b0 y
b0 x
b0 w
b0 v
b0 u
b0 t
b0 s
b0 r
b0 q
b0 p
b0 o
b0 n
b0 m
b0 l
b0 k
b1001 j
bx i
b0 h
b0 g
b0 f
b0 e
b0 d
b0 c
b0 b
b0 a
b0 `
b0 _
b0 ^
b0 ]
b0 \
b0 [
b0 Z
b0 Y
b0 X
b0 W
b0 V
b0 U
b0 T
b0 S
b0 R
b0 Q
b0 P
b0 O
b0 N
b0 M
b0 L
b0 K
b0 J
b0 I
b0 H
b0 G
b0 F
b0 E
b0 D
b0 C
b0 B
b0 A
b0 @
b0 ?
b0 >
b0 =
b0 <
b0 ;
b0 :
b0 9
b0 8
b0 7
b0 6
b0 5
b0 4
b0 3
b0 2
b0 1
bx 0
bx /
bx .
bx -
bx ,
bx +
bx *
bx )
bx (
1'
bx &
bx %
bx $
0#
0"
b0 !
$end
#5000
1#
#10000
0#
b110000000000000111000000000000001000000000000000000000000000000000 &
b110000000000000111000000000000001000000000000000000000000000000000 -
b1000000000000011000000000000010000000000000000000 %
b1000000000000011000000000000010000000000000000000 ,
b10000000000000000110000000000000111 $
b10000000000000000110000000000000111 +
b1010000000000000100000000000000011100000000000000000000000000000000 *
b1010000000000000100000000000000011100000000000000000000000000000000 0
b1001000000000000100000000000000001010000000000000000 )
b1001000000000000100000000000000001010000000000000000 /
b10000000000000000110000000000000001 (
b10000000000000000110000000000000001 .
0'
#15000
b111 3
b1 4
b1 2
1#
#20000
0#
#25000
b1000 9
b11 3
b101 F
b11 4
b10 2
b1 6
b1 :
b1 l
b111 7
b111 E
b111 k
b111 !
b111 1
b111 5
1#
#30000
0#
#35000
b11 6
b11 :
b11 l
b11 7
b11 E
b11 k
b10000 5
b1 <
b1 @
b1 n
b1000 =
b1000 K
b1000 m
b1000 ;
b101 H
b101 L
b101 r
b111 I
b111 W
b111 q
b100011000000000000000000000000000000000000000000000000000000000000100000000000000000000000000000010000 !
b100011000000000000000000000000000000000000000000000000000000000000100000000000000000000000000000010000 1
b100011 G
b10 ?
b110 9
b100 3
b111 X
b1000 F
b100 4
b11 2
1#
#40000
0#
#45000
b111 ?
b1 9
b0 3
b100 X
b1001 F
b0 4
b100 2
b111 Z
b111 ^
b111 x
b111 [
b111 w
b110001 Y
b101 N
b101 R
b101 t
b1000 O
b1000 ]
b1000 s
b101000 M
b1000 H
b1000 L
b1000 r
b11 I
b11 W
b11 q
b111011 G
b1 B
b1 p
b10 C
b10 Q
b10 o
b10 A
b11 <
b11 @
b11 n
b110 =
b110 K
b110 m
b11010 ;
b100 6
b100 :
b100 l
b100 7
b100 E
b100 k
b110001000000000000000000000000000000000000000000000000000000000010100000000000000000000000000000111011000000000000000000000000000000100000000000000000000000000001101000000000000000000000000000100000 !
b110001000000000000000000000000000000000000000000000000000000000010100000000000000000000000000000111011000000000000000000000000000000100000000000000000000000000001101000000000000000000000000000100000 1
b100000 5
1#
#50000
0#
#55000
b0 6
b0 :
b0 l
b0 7
b0 E
b0 k
b100 <
b100 @
b100 n
b1 =
b1 K
b1 m
b11110 ;
b11 B
b11 p
b111 C
b111 Q
b111 o
b10111 A
b1001 H
b1001 L
b1001 r
b100 I
b100 W
b100 q
b1011111 G
b1000 N
b1000 R
b1000 t
b110 O
b110 ]
b110 s
b1011000 M
b101 T
b101 v
b10 U
b10 c
b10 u
b1010 S
b100 Z
b100 ^
b100 x
b11 [
b11 w
b111101 Y
b111 `
b111 d
b111 z
b1000 a
b1000 y
b11100000000000000000000000000000111101000000000000000000000000000010100000000000000000000000000101100000000000000000000000000001011111000000000000000000000000000101110000000000000000000000000001111000000000000000000000000000100000 !
b11100000000000000000000000000000111101000000000000000000000000000010100000000000000000000000000101100000000000000000000000000001011111000000000000000000000000000101110000000000000000000000000001111000000000000000000000000000100000 1
b111000 _
b11 ?
b0 9
b101 X
b0 F
b101 2
1#
#60000
0#
#65000
b110 2
b111 f
b111 |
b10 g
b10 {
b1110 e
b100 `
b100 d
b100 z
b110 a
b110 y
b1010000 _
b101 Z
b101 ^
b101 x
b100 [
b100 w
b1010001 Y
b1000 T
b1000 v
b111 U
b111 c
b111 u
b1000010 S
b1001 N
b1001 R
b1001 t
b1 O
b1 ]
b1 s
b1100001 M
b0 H
b0 L
b0 r
b0 I
b0 W
b0 q
b100 B
b100 p
b11 C
b11 Q
b11 o
b11100000000000000000000000000101000000000000000000000000000001010001000000000000000000000000010000100000000000000000000000000110000100000000000000000000000001011111000000000000000000000000001000110000000000000000000000000001111000000000000000000000000000100000 !
b11100000000000000000000000000101000000000000000000000000000001010001000000000000000000000000010000100000000000000000000000000110000100000000000000000000000001011111000000000000000000000000001000110000000000000000000000000001111000000000000000000000000000100000 1
b100011 A
b0 <
b0 @
b0 n
b0 =
b0 K
b0 m
1#
#70000
0#
#75000
b0 B
b0 p
b0 N
b0 R
b0 t
b0 O
b0 ]
b0 s
b1001 T
b1001 v
b11 U
b11 c
b11 u
b1011101 S
b0 [
b0 w
b101 `
b101 d
b101 z
b1 a
b1 y
b1010101 _
b100 f
b100 |
b111 g
b111 {
b1010100000000000000000000000000101010100000000000000000000000001010001000000000000000000000000010111010000000000000000000000000110000100000000000000000000000001011111000000000000000000000000001000110000000000000000000000000001111000000000000000000000000000100000 !
b1010100000000000000000000000000101010100000000000000000000000001010001000000000000000000000000010111010000000000000000000000000110000100000000000000000000000001011111000000000000000000000000001000110000000000000000000000000001111000000000000000000000000000100000 1
b101010 e
1"
1#
#80000
0#
#85000
b101 f
b101 |
b11 g
b11 {
b1110010000000000000000000000000101010100000000000000000000000001010001000000000000000000000000010111010000000000000000000000000110000100000000000000000000000001011111000000000000000000000000001000110000000000000000000000000001111000000000000000000000000000100000 !
b1110010000000000000000000000000101010100000000000000000000000001010001000000000000000000000000010111010000000000000000000000000110000100000000000000000000000001011111000000000000000000000000001000110000000000000000000000000001111000000000000000000000000000100000 1
b111001 e
b0 a
b0 y
b0 T
b0 v
1#
#90000
0#
#95000
b10010000000000000000000000000000101010100000000000000000000000001010001000000000000000000000000010111010000000000000000000000000110000100000000000000000000000001011111000000000000000000000000001000110000000000000000000000000001111000000000000000000000000000100000 !
b10010000000000000000000000000000101010100000000000000000000000001010001000000000000000000000000010111010000000000000000000000000110000100000000000000000000000001011111000000000000000000000000001000110000000000000000000000000001111000000000000000000000000000100000 1
b1001000 e
1#
#100000
0#
#105000
b10101110000000000000000000000000101010100000000000000000000000001010001000000000000000000000000010111010000000000000000000000000110000100000000000000000000000001011111000000000000000000000000001000110000000000000000000000000001111000000000000000000000000000100000 !
b10101110000000000000000000000000101010100000000000000000000000001010001000000000000000000000000010111010000000000000000000000000110000100000000000000000000000001011111000000000000000000000000001000110000000000000000000000000001111000000000000000000000000000100000 1
b1010111 e
1#
#110000
0#
#115000
b11001100000000000000000000000000101010100000000000000000000000001010001000000000000000000000000010111010000000000000000000000000110000100000000000000000000000001011111000000000000000000000000001000110000000000000000000000000001111000000000000000000000000000100000 !
b11001100000000000000000000000000101010100000000000000000000000001010001000000000000000000000000010111010000000000000000000000000110000100000000000000000000000001011111000000000000000000000000001000110000000000000000000000000001111000000000000000000000000000100000 1
b1100110 e
1#
#120000
0#
#125000
b11101010000000000000000000000000101010100000000000000000000000001010001000000000000000000000000010111010000000000000000000000000110000100000000000000000000000001011111000000000000000000000000001000110000000000000000000000000001111000000000000000000000000000100000 !
b11101010000000000000000000000000101010100000000000000000000000001010001000000000000000000000000010111010000000000000000000000000110000100000000000000000000000001011111000000000000000000000000001000110000000000000000000000000001111000000000000000000000000000100000 1
b1110101 e
1#
#130000
0#
#135000
b100001000000000000000000000000000101010100000000000000000000000001010001000000000000000000000000010111010000000000000000000000000110000100000000000000000000000001011111000000000000000000000000001000110000000000000000000000000001111000000000000000000000000000100000 !
b100001000000000000000000000000000101010100000000000000000000000001010001000000000000000000000000010111010000000000000000000000000110000100000000000000000000000001011111000000000000000000000000001000110000000000000000000000000001111000000000000000000000000000100000 1
b10000100 e
1#
#140000
0#
#145000
b100100110000000000000000000000000101010100000000000000000000000001010001000000000000000000000000010111010000000000000000000000000110000100000000000000000000000001011111000000000000000000000000001000110000000000000000000000000001111000000000000000000000000000100000 !
b100100110000000000000000000000000101010100000000000000000000000001010001000000000000000000000000010111010000000000000000000000000110000100000000000000000000000001011111000000000000000000000000001000110000000000000000000000000001111000000000000000000000000000100000 1
b10010011 e
1#
#150000
0#
#155000
b101000100000000000000000000000000101010100000000000000000000000001010001000000000000000000000000010111010000000000000000000000000110000100000000000000000000000001011111000000000000000000000000001000110000000000000000000000000001111000000000000000000000000000100000 !
b101000100000000000000000000000000101010100000000000000000000000001010001000000000000000000000000010111010000000000000000000000000110000100000000000000000000000001011111000000000000000000000000001000110000000000000000000000000001111000000000000000000000000000100000 1
b10100010 e
1#
#160000
0#
#165000
b101100010000000000000000000000000101010100000000000000000000000001010001000000000000000000000000010111010000000000000000000000000110000100000000000000000000000001011111000000000000000000000000001000110000000000000000000000000001111000000000000000000000000000100000 !
b101100010000000000000000000000000101010100000000000000000000000001010001000000000000000000000000010111010000000000000000000000000110000100000000000000000000000001011111000000000000000000000000001000110000000000000000000000000001111000000000000000000000000000100000 1
b10110001 e
1#
#170000
0#
#175000
b110000000000000000000000000000000101010100000000000000000000000001010001000000000000000000000000010111010000000000000000000000000110000100000000000000000000000001011111000000000000000000000000001000110000000000000000000000000001111000000000000000000000000000100000 !
b110000000000000000000000000000000101010100000000000000000000000001010001000000000000000000000000010111010000000000000000000000000110000100000000000000000000000001011111000000000000000000000000001000110000000000000000000000000001111000000000000000000000000000100000 1
b11000000 e
1#
#180000
0#
#185000
b110011110000000000000000000000000101010100000000000000000000000001010001000000000000000000000000010111010000000000000000000000000110000100000000000000000000000001011111000000000000000000000000001000110000000000000000000000000001111000000000000000000000000000100000 !
b110011110000000000000000000000000101010100000000000000000000000001010001000000000000000000000000010111010000000000000000000000000110000100000000000000000000000001011111000000000000000000000000001000110000000000000000000000000001111000000000000000000000000000100000 1
b11001111 e
1#
#190000
0#
#195000
b110111100000000000000000000000000101010100000000000000000000000001010001000000000000000000000000010111010000000000000000000000000110000100000000000000000000000001011111000000000000000000000000001000110000000000000000000000000001111000000000000000000000000000100000 !
b110111100000000000000000000000000101010100000000000000000000000001010001000000000000000000000000010111010000000000000000000000000110000100000000000000000000000001011111000000000000000000000000001000110000000000000000000000000001111000000000000000000000000000100000 1
b11011110 e
1#
#200000
0#
#205000
b111011010000000000000000000000000101010100000000000000000000000001010001000000000000000000000000010111010000000000000000000000000110000100000000000000000000000001011111000000000000000000000000001000110000000000000000000000000001111000000000000000000000000000100000 !
b111011010000000000000000000000000101010100000000000000000000000001010001000000000000000000000000010111010000000000000000000000000110000100000000000000000000000001011111000000000000000000000000001000110000000000000000000000000001111000000000000000000000000000100000 1
b11101101 e
1#
#210000
0#
#215000
b111111000000000000000000000000000101010100000000000000000000000001010001000000000000000000000000010111010000000000000000000000000110000100000000000000000000000001011111000000000000000000000000001000110000000000000000000000000001111000000000000000000000000000100000 !
b111111000000000000000000000000000101010100000000000000000000000001010001000000000000000000000000010111010000000000000000000000000110000100000000000000000000000001011111000000000000000000000000001000110000000000000000000000000001111000000000000000000000000000100000 1
b11111100 e
1#
#220000
0#
#225000
b1000010110000000000000000000000000101010100000000000000000000000001010001000000000000000000000000010111010000000000000000000000000110000100000000000000000000000001011111000000000000000000000000001000110000000000000000000000000001111000000000000000000000000000100000 !
b1000010110000000000000000000000000101010100000000000000000000000001010001000000000000000000000000010111010000000000000000000000000110000100000000000000000000000001011111000000000000000000000000001000110000000000000000000000000001111000000000000000000000000000100000 1
b100001011 e
1#
#230000
0#
#235000
b1000110100000000000000000000000000101010100000000000000000000000001010001000000000000000000000000010111010000000000000000000000000110000100000000000000000000000001011111000000000000000000000000001000110000000000000000000000000001111000000000000000000000000000100000 !
b1000110100000000000000000000000000101010100000000000000000000000001010001000000000000000000000000010111010000000000000000000000000110000100000000000000000000000001011111000000000000000000000000001000110000000000000000000000000001111000000000000000000000000000100000 1
b100011010 e
1#
#240000
0#
#245000
b1001010010000000000000000000000000101010100000000000000000000000001010001000000000000000000000000010111010000000000000000000000000110000100000000000000000000000001011111000000000000000000000000001000110000000000000000000000000001111000000000000000000000000000100000 !
b1001010010000000000000000000000000101010100000000000000000000000001010001000000000000000000000000010111010000000000000000000000000110000100000000000000000000000001011111000000000000000000000000001000110000000000000000000000000001111000000000000000000000000000100000 1
b100101001 e
1#
#250000
0#
#255000
b1001110000000000000000000000000000101010100000000000000000000000001010001000000000000000000000000010111010000000000000000000000000110000100000000000000000000000001011111000000000000000000000000001000110000000000000000000000000001111000000000000000000000000000100000 !
b1001110000000000000000000000000000101010100000000000000000000000001010001000000000000000000000000010111010000000000000000000000000110000100000000000000000000000001011111000000000000000000000000001000110000000000000000000000000001111000000000000000000000000000100000 1
b100111000 e
1#
#260000
0#
#265000
b1010001110000000000000000000000000101010100000000000000000000000001010001000000000000000000000000010111010000000000000000000000000110000100000000000000000000000001011111000000000000000000000000001000110000000000000000000000000001111000000000000000000000000000100000 !
b1010001110000000000000000000000000101010100000000000000000000000001010001000000000000000000000000010111010000000000000000000000000110000100000000000000000000000001011111000000000000000000000000001000110000000000000000000000000001111000000000000000000000000000100000 1
b101000111 e
1#
#270000
0#
#275000
b1010101100000000000000000000000000101010100000000000000000000000001010001000000000000000000000000010111010000000000000000000000000110000100000000000000000000000001011111000000000000000000000000001000110000000000000000000000000001111000000000000000000000000000100000 !
b1010101100000000000000000000000000101010100000000000000000000000001010001000000000000000000000000010111010000000000000000000000000110000100000000000000000000000001011111000000000000000000000000001000110000000000000000000000000001111000000000000000000000000000100000 1
b101010110 e
1#
#280000
0#
#285000
b1011001010000000000000000000000000101010100000000000000000000000001010001000000000000000000000000010111010000000000000000000000000110000100000000000000000000000001011111000000000000000000000000001000110000000000000000000000000001111000000000000000000000000000100000 !
b1011001010000000000000000000000000101010100000000000000000000000001010001000000000000000000000000010111010000000000000000000000000110000100000000000000000000000001011111000000000000000000000000001000110000000000000000000000000001111000000000000000000000000000100000 1
b101100101 e
1#
#290000
0#
#295000
b1011101000000000000000000000000000101010100000000000000000000000001010001000000000000000000000000010111010000000000000000000000000110000100000000000000000000000001011111000000000000000000000000001000110000000000000000000000000001111000000000000000000000000000100000 !
b1011101000000000000000000000000000101010100000000000000000000000001010001000000000000000000000000010111010000000000000000000000000110000100000000000000000000000001011111000000000000000000000000001000110000000000000000000000000001111000000000000000000000000000100000 1
b101110100 e
1#
#300000
0#
#305000
b1100000110000000000000000000000000101010100000000000000000000000001010001000000000000000000000000010111010000000000000000000000000110000100000000000000000000000001011111000000000000000000000000001000110000000000000000000000000001111000000000000000000000000000100000 !
b1100000110000000000000000000000000101010100000000000000000000000001010001000000000000000000000000010111010000000000000000000000000110000100000000000000000000000001011111000000000000000000000000001000110000000000000000000000000001111000000000000000000000000000100000 1
b110000011 e
1#
#310000
0#
#315000
b1100100100000000000000000000000000101010100000000000000000000000001010001000000000000000000000000010111010000000000000000000000000110000100000000000000000000000001011111000000000000000000000000001000110000000000000000000000000001111000000000000000000000000000100000 !
b1100100100000000000000000000000000101010100000000000000000000000001010001000000000000000000000000010111010000000000000000000000000110000100000000000000000000000001011111000000000000000000000000001000110000000000000000000000000001111000000000000000000000000000100000 1
b110010010 e
1#
#320000
0#
#325000
b1101000010000000000000000000000000101010100000000000000000000000001010001000000000000000000000000010111010000000000000000000000000110000100000000000000000000000001011111000000000000000000000000001000110000000000000000000000000001111000000000000000000000000000100000 !
b1101000010000000000000000000000000101010100000000000000000000000001010001000000000000000000000000010111010000000000000000000000000110000100000000000000000000000001011111000000000000000000000000001000110000000000000000000000000001111000000000000000000000000000100000 1
b110100001 e
1#
#330000
0#
#335000
b1101100000000000000000000000000000101010100000000000000000000000001010001000000000000000000000000010111010000000000000000000000000110000100000000000000000000000001011111000000000000000000000000001000110000000000000000000000000001111000000000000000000000000000100000 !
b1101100000000000000000000000000000101010100000000000000000000000001010001000000000000000000000000010111010000000000000000000000000110000100000000000000000000000001011111000000000000000000000000001000110000000000000000000000000001111000000000000000000000000000100000 1
b110110000 e
1#
#340000
0#
#345000
b1101111110000000000000000000000000101010100000000000000000000000001010001000000000000000000000000010111010000000000000000000000000110000100000000000000000000000001011111000000000000000000000000001000110000000000000000000000000001111000000000000000000000000000100000 !
b1101111110000000000000000000000000101010100000000000000000000000001010001000000000000000000000000010111010000000000000000000000000110000100000000000000000000000001011111000000000000000000000000001000110000000000000000000000000001111000000000000000000000000000100000 1
b110111111 e
1#
#350000
0#
#355000
b1110011100000000000000000000000000101010100000000000000000000000001010001000000000000000000000000010111010000000000000000000000000110000100000000000000000000000001011111000000000000000000000000001000110000000000000000000000000001111000000000000000000000000000100000 !
b1110011100000000000000000000000000101010100000000000000000000000001010001000000000000000000000000010111010000000000000000000000000110000100000000000000000000000001011111000000000000000000000000001000110000000000000000000000000001111000000000000000000000000000100000 1
b111001110 e
1#
#360000
0#
#365000
b1110111010000000000000000000000000101010100000000000000000000000001010001000000000000000000000000010111010000000000000000000000000110000100000000000000000000000001011111000000000000000000000000001000110000000000000000000000000001111000000000000000000000000000100000 !
b1110111010000000000000000000000000101010100000000000000000000000001010001000000000000000000000000010111010000000000000000000000000110000100000000000000000000000001011111000000000000000000000000001000110000000000000000000000000001111000000000000000000000000000100000 1
b111011101 e
1#
#370000
0#
#375000
b1111011000000000000000000000000000101010100000000000000000000000001010001000000000000000000000000010111010000000000000000000000000110000100000000000000000000000001011111000000000000000000000000001000110000000000000000000000000001111000000000000000000000000000100000 !
b1111011000000000000000000000000000101010100000000000000000000000001010001000000000000000000000000010111010000000000000000000000000110000100000000000000000000000001011111000000000000000000000000001000110000000000000000000000000001111000000000000000000000000000100000 1
b111101100 e
1#
#380000
0#
#385000
b1111110110000000000000000000000000101010100000000000000000000000001010001000000000000000000000000010111010000000000000000000000000110000100000000000000000000000001011111000000000000000000000000001000110000000000000000000000000001111000000000000000000000000000100000 !
b1111110110000000000000000000000000101010100000000000000000000000001010001000000000000000000000000010111010000000000000000000000000110000100000000000000000000000001011111000000000000000000000000001000110000000000000000000000000001111000000000000000000000000000100000 1
b111111011 e
1#
#390000
0#
#395000
b10000010100000000000000000000000000101010100000000000000000000000001010001000000000000000000000000010111010000000000000000000000000110000100000000000000000000000001011111000000000000000000000000001000110000000000000000000000000001111000000000000000000000000000100000 !
b10000010100000000000000000000000000101010100000000000000000000000001010001000000000000000000000000010111010000000000000000000000000110000100000000000000000000000001011111000000000000000000000000001000110000000000000000000000000001111000000000000000000000000000100000 1
b1000001010 e
1#
#400000
0#
#405000
b10000110010000000000000000000000000101010100000000000000000000000001010001000000000000000000000000010111010000000000000000000000000110000100000000000000000000000001011111000000000000000000000000001000110000000000000000000000000001111000000000000000000000000000100000 !
b10000110010000000000000000000000000101010100000000000000000000000001010001000000000000000000000000010111010000000000000000000000000110000100000000000000000000000001011111000000000000000000000000001000110000000000000000000000000001111000000000000000000000000000100000 1
b1000011001 e
1#
#410000
0#
#415000
b10001010000000000000000000000000000101010100000000000000000000000001010001000000000000000000000000010111010000000000000000000000000110000100000000000000000000000001011111000000000000000000000000001000110000000000000000000000000001111000000000000000000000000000100000 !
b10001010000000000000000000000000000101010100000000000000000000000001010001000000000000000000000000010111010000000000000000000000000110000100000000000000000000000001011111000000000000000000000000001000110000000000000000000000000001111000000000000000000000000000100000 1
b1000101000 e
1#
